[
  {
    "timeframe": "5m",
    "horizon": 6,
    "source_group": "agg_trade_pressure",
    "feature": "taker_buy_quote_ratio_trades",
    "sample_size": 158,
    "correlation": -0.1712845121409379,
    "abs_correlation": 0.1712845121409379,
    "quantile_spread": 0.09365828340042755,
    "lowest_bucket_avg_return_pct": 0.04744863021683452,
    "highest_bucket_avg_return_pct": -0.04556616009741366,
    "lowest_bucket_win_rate": 0.5806451612903226,
    "highest_bucket_win_rate": 0.28125,
    "usable_for_strategy_research": true,
    "reason": "candidate_research_only"
  },
  {
    "timeframe": "5m",
    "horizon": 6,
    "source_group": "agg_trade_pressure",
    "feature": "taker_buy_base_ratio_trades",
    "sample_size": 158,
    "correlation": -0.17127017744365505,
    "abs_correlation": 0.17127017744365505,
    "quantile_spread": 0.09365828340042755,
    "lowest_bucket_avg_return_pct": 0.04744863021683452,
    "highest_bucket_avg_return_pct": -0.04556616009741366,
    "lowest_bucket_win_rate": 0.5806451612903226,
    "highest_bucket_win_rate": 0.28125,
    "usable_for_strategy_research": true,
    "reason": "candidate_research_only"
  },
  {
    "timeframe": "5m",
    "horizon": 6,
    "source_group": "agg_trade_pressure",
    "feature": "taker_net_quote_volume",
    "sample_size": 158,
    "correlation": -0.16787659186266485,
    "abs_correlation": 0.16787659186266485,
    "quantile_spread": 0.07914548620717879,
    "lowest_bucket_avg_return_pct": 0.031894773460213625,
    "highest_bucket_avg_return_pct": -0.04725071274696516,
    "lowest_bucket_win_rate": 0.4838709677419355,
    "highest_bucket_win_rate": 0.3125,
    "usable_for_strategy_research": true,
    "reason": "candidate_research_only"
  },
  {
    "timeframe": "5m",
    "horizon": 6,
    "source_group": "agg_trade_pressure",
    "feature": "taker_net_base_volume",
    "sample_size": 158,
    "correlation": -0.1677121616423901,
    "abs_correlation": 0.1677121616423901,
    "quantile_spread": 0.08478398623411831,
    "lowest_bucket_avg_return_pct": 0.031894773460213625,
    "highest_bucket_avg_return_pct": -0.052889212773904695,
    "lowest_bucket_win_rate": 0.4838709677419355,
    "highest_bucket_win_rate": 0.28125,
    "usable_for_strategy_research": true,
    "reason": "candidate_research_only"
  },
  {
    "timeframe": "5m",
    "horizon": 1,
    "source_group": "agg_trade_pressure",
    "feature": "taker_buy_quote_ratio_trades",
    "sample_size": 158,
    "correlation": -0.15950455286418133,
    "abs_correlation": 0.15950455286418133,
    "quantile_spread": 0.029548914723559114,
    "lowest_bucket_avg_return_pct": 0.009046653621139484,
    "highest_bucket_avg_return_pct": -0.012979452456126653,
    "lowest_bucket_win_rate": 0.6129032258064516,
    "highest_bucket_win_rate": 0.40625,
    "usable_for_strategy_research": true,
    "reason": "candidate_research_only"
  },
  {
    "timeframe": "5m",
    "horizon": 1,
    "source_group": "agg_trade_pressure",
    "feature": "taker_buy_base_ratio_trades",
    "sample_size": 158,
    "correlation": -0.15948830038706827,
    "abs_correlation": 0.15948830038706827,
    "quantile_spread": 0.029548914723559114,
    "lowest_bucket_avg_return_pct": 0.009046653621139484,
    "highest_bucket_avg_return_pct": -0.012979452456126653,
    "lowest_bucket_win_rate": 0.6129032258064516,
    "highest_bucket_win_rate": 0.40625,
    "usable_for_strategy_research": true,
    "reason": "candidate_research_only"
  },
  {
    "timeframe": "5m",
    "horizon": 3,
    "source_group": "agg_trade_pressure",
    "feature": "avg_trade_quote_size",
    "sample_size": 158,
    "correlation": 0.1490362502238427,
    "abs_correlation": 0.1490362502238427,
    "quantile_spread": 0.10245289783039592,
    "lowest_bucket_avg_return_pct": 0.0015745592387891355,
    "highest_bucket_avg_return_pct": 0.0330332059606111,
    "lowest_bucket_win_rate": 0.5806451612903226,
    "highest_bucket_win_rate": 0.59375,
    "usable_for_strategy_research": true,
    "reason": "candidate_research_only"
  },
  {
    "timeframe": "5m",
    "horizon": 1,
    "source_group": "agg_trade_pressure",
    "feature": "taker_net_quote_volume",
    "sample_size": 158,
    "correlation": -0.12793807528535478,
    "abs_correlation": 0.12793807528535478,
    "quantile_spread": 0.046499315606158415,
    "lowest_bucket_avg_return_pct": 0.026844140296687982,
    "highest_bucket_avg_return_pct": -0.015155953273957848,
    "lowest_bucket_win_rate": 0.7096774193548387,
    "highest_bucket_win_rate": 0.4375,
    "usable_for_strategy_research": true,
    "reason": "candidate_research_only"
  },
  {
    "timeframe": "5m",
    "horizon": 1,
    "source_group": "agg_trade_pressure",
    "feature": "taker_net_base_volume",
    "sample_size": 158,
    "correlation": -0.12793417274155325,
    "abs_correlation": 0.12793417274155325,
    "quantile_spread": 0.044934181480283025,
    "lowest_bucket_avg_return_pct": 0.026844140296687982,
    "highest_bucket_avg_return_pct": -0.018090041183595047,
    "lowest_bucket_win_rate": 0.7096774193548387,
    "highest_bucket_win_rate": 0.40625,
    "usable_for_strategy_research": true,
    "reason": "candidate_research_only"
  },
  {
    "timeframe": "5m",
    "horizon": 3,
    "source_group": "agg_trade_pressure",
    "feature": "taker_buy_quote_ratio_trades",
    "sample_size": 158,
    "correlation": -0.12643227864860845,
    "abs_correlation": 0.12643227864860845,
    "quantile_spread": 0.034982703048588894,
    "lowest_bucket_avg_return_pct": 0.007722050396940945,
    "highest_bucket_avg_return_pct": -0.02726065265164795,
    "lowest_bucket_win_rate": 0.5161290322580645,
    "highest_bucket_win_rate": 0.3125,
    "usable_for_strategy_research": true,
    "reason": "candidate_research_only"
  },
  {
    "timeframe": "5m",
    "horizon": 3,
    "source_group": "agg_trade_pressure",
    "feature": "taker_buy_base_ratio_trades",
    "sample_size": 158,
    "correlation": -0.1264228635896465,
    "abs_correlation": 0.1264228635896465,
    "quantile_spread": 0.034982703048588894,
    "lowest_bucket_avg_return_pct": 0.007722050396940945,
    "highest_bucket_avg_return_pct": -0.02726065265164795,
    "lowest_bucket_win_rate": 0.5161290322580645,
    "highest_bucket_win_rate": 0.3125,
    "usable_for_strategy_research": true,
    "reason": "candidate_research_only"
  },
  {
    "timeframe": "1m",
    "horizon": 6,
    "source_group": "live_order_book",
    "feature": "imbalance_top_5",
    "sample_size": 216,
    "correlation": 0.12260046060900748,
    "abs_correlation": 0.12260046060900748,
    "quantile_spread": 0.08906310846182894,
    "lowest_bucket_avg_return_pct": -0.008502112657485525,
    "highest_bucket_avg_return_pct": 0.08056099580434341,
    "lowest_bucket_win_rate": 0.5116279069767442,
    "highest_bucket_win_rate": 0.5227272727272727,
    "usable_for_strategy_research": true,
    "reason": "candidate_research_only"
  },
  {
    "timeframe": "1m",
    "horizon": 6,
    "source_group": "live_order_book",
    "feature": "order_book_imbalance",
    "sample_size": 216,
    "correlation": 0.12090745712349377,
    "abs_correlation": 0.12090745712349377,
    "quantile_spread": 0.1366196314265466,
    "lowest_bucket_avg_return_pct": -0.00550461223424217,
    "highest_bucket_avg_return_pct": 0.07179098766159586,
    "lowest_bucket_win_rate": 0.5348837209302325,
    "highest_bucket_win_rate": 0.5454545454545454,
    "usable_for_strategy_research": true,
    "reason": "candidate_research_only"
  },
  {
    "timeframe": "1m",
    "horizon": 6,
    "source_group": "live_order_book",
    "feature": "imbalance_top_10",
    "sample_size": 216,
    "correlation": 0.12090745712349377,
    "abs_correlation": 0.12090745712349377,
    "quantile_spread": 0.1366196314265466,
    "lowest_bucket_avg_return_pct": -0.00550461223424217,
    "highest_bucket_avg_return_pct": 0.07179098766159586,
    "lowest_bucket_win_rate": 0.5348837209302325,
    "highest_bucket_win_rate": 0.5454545454545454,
    "usable_for_strategy_research": true,
    "reason": "candidate_research_only"
  },
  {
    "timeframe": "1m",
    "horizon": 3,
    "source_group": "agg_trade_pressure",
    "feature": "taker_buy_base_ratio_trades",
    "sample_size": 790,
    "correlation": -0.11949997397301242,
    "abs_correlation": 0.11949997397301242,
    "quantile_spread": 0.021508406808358138,
    "lowest_bucket_avg_return_pct": 0.004948414689180631,
    "highest_bucket_avg_return_pct": -0.012461286465699776,
    "lowest_bucket_win_rate": 0.5316455696202531,
    "highest_bucket_win_rate": 0.4177215189873418,
    "usable_for_strategy_research": true,
    "reason": "candidate_research_only"
  },
  {
    "timeframe": "1m",
    "horizon": 3,
    "source_group": "agg_trade_pressure",
    "feature": "taker_buy_quote_ratio_trades",
    "sample_size": 790,
    "correlation": -0.11949848709621094,
    "abs_correlation": 0.11949848709621094,
    "quantile_spread": 0.021508406808358138,
    "lowest_bucket_avg_return_pct": 0.004948414689180631,
    "highest_bucket_avg_return_pct": -0.012461286465699776,
    "lowest_bucket_win_rate": 0.5316455696202531,
    "highest_bucket_win_rate": 0.4177215189873418,
    "usable_for_strategy_research": true,
    "reason": "candidate_research_only"
  },
  {
    "timeframe": "5m",
    "horizon": 6,
    "source_group": "agg_trade_pressure",
    "feature": "avg_trade_quote_size",
    "sample_size": 158,
    "correlation": 0.11172089554540394,
    "abs_correlation": 0.11172089554540394,
    "quantile_spread": 0.05085806122527565,
    "lowest_bucket_avg_return_pct": -0.008266029566543572,
    "highest_bucket_avg_return_pct": 0.0002849748564371612,
    "lowest_bucket_win_rate": 0.6451612903225806,
    "highest_bucket_win_rate": 0.40625,
    "usable_for_strategy_research": true,
    "reason": "candidate_research_only"
  },
  {
    "timeframe": "1m",
    "horizon": 6,
    "source_group": "agg_trade_pressure",
    "feature": "taker_buy_quote_ratio_trades",
    "sample_size": 790,
    "correlation": -0.10326920609902247,
    "abs_correlation": 0.10326920609902247,
    "quantile_spread": 0.02564281811006583,
    "lowest_bucket_avg_return_pct": 0.006305561780646433,
    "highest_bucket_avg_return_pct": -0.01761329947193465,
    "lowest_bucket_win_rate": 0.5632911392405063,
    "highest_bucket_win_rate": 0.43037974683544306,
    "usable_for_strategy_research": true,
    "reason": "candidate_research_only"
  },
  {
    "timeframe": "1m",
    "horizon": 6,
    "source_group": "agg_trade_pressure",
    "feature": "taker_buy_base_ratio_trades",
    "sample_size": 790,
    "correlation": -0.10326544399317197,
    "abs_correlation": 0.10326544399317197,
    "quantile_spread": 0.02564281811006583,
    "lowest_bucket_avg_return_pct": 0.006305561780646433,
    "highest_bucket_avg_return_pct": -0.01761329947193465,
    "lowest_bucket_win_rate": 0.5632911392405063,
    "highest_bucket_win_rate": 0.43037974683544306,
    "usable_for_strategy_research": true,
    "reason": "candidate_research_only"
  },
  {
    "timeframe": "1m",
    "horizon": 6,
    "source_group": "live_order_book",
    "feature": "imbalance_top_20",
    "sample_size": 216,
    "correlation": 0.10311669033873849,
    "abs_correlation": 0.10311669033873849,
    "quantile_spread": 0.11894766708552972,
    "lowest_bucket_avg_return_pct": 0.004988664653434956,
    "highest_bucket_avg_return_pct": 0.05398735204464302,
    "lowest_bucket_win_rate": 0.5348837209302325,
    "highest_bucket_win_rate": 0.5,
    "usable_for_strategy_research": true,
    "reason": "candidate_research_only"
  },
  {
    "timeframe": "1m",
    "horizon": 3,
    "source_group": "agg_trade_pressure",
    "feature": "taker_buy_trade_ratio",
    "sample_size": 790,
    "correlation": -0.1011943668924145,
    "abs_correlation": 0.1011943668924145,
    "quantile_spread": 0.016379984335227,
    "lowest_bucket_avg_return_pct": 0.004146348874244779,
    "highest_bucket_avg_return_pct": -0.010986011445833173,
    "lowest_bucket_win_rate": 0.5,
    "highest_bucket_win_rate": 0.4240506329113924,
    "usable_for_strategy_research": true,
    "reason": "candidate_research_only"
  },
  {
    "timeframe": "1m",
    "horizon": 3,
    "source_group": "agg_trade_pressure",
    "feature": "taker_net_quote_volume",
    "sample_size": 790,
    "correlation": -0.09403129187506498,
    "abs_correlation": 0.09403129187506498,
    "quantile_spread": 0.02802183028414043,
    "lowest_bucket_avg_return_pct": 0.0024567727006827847,
    "highest_bucket_avg_return_pct": -0.018313811048095544,
    "lowest_bucket_win_rate": 0.5189873417721519,
    "highest_bucket_win_rate": 0.3860759493670886,
    "usable_for_strategy_research": true,
    "reason": "candidate_research_only"
  },
  {
    "timeframe": "1m",
    "horizon": 3,
    "source_group": "agg_trade_pressure",
    "feature": "taker_net_base_volume",
    "sample_size": 790,
    "correlation": -0.09400796515525468,
    "abs_correlation": 0.09400796515525468,
    "quantile_spread": 0.02802183028414043,
    "lowest_bucket_avg_return_pct": 0.0024567727006827847,
    "highest_bucket_avg_return_pct": -0.018313811048095544,
    "lowest_bucket_win_rate": 0.5189873417721519,
    "highest_bucket_win_rate": 0.3860759493670886,
    "usable_for_strategy_research": true,
    "reason": "candidate_research_only"
  },
  {
    "timeframe": "1m",
    "horizon": 1,
    "source_group": "agg_trade_pressure",
    "feature": "taker_net_base_volume",
    "sample_size": 790,
    "correlation": -0.09155104353718457,
    "abs_correlation": 0.09155104353718457,
    "quantile_spread": 0.01267369207272958,
    "lowest_bucket_avg_return_pct": 0.0011093680935691408,
    "highest_bucket_avg_return_pct": -0.009134359279863901,
    "lowest_bucket_win_rate": 0.5126582278481012,
    "highest_bucket_win_rate": 0.3924050632911392,
    "usable_for_strategy_research": true,
    "reason": "candidate_research_only"
  },
  {
    "timeframe": "1m",
    "horizon": 1,
    "source_group": "agg_trade_pressure",
    "feature": "taker_net_quote_volume",
    "sample_size": 790,
    "correlation": -0.09148487281542052,
    "abs_correlation": 0.09148487281542052,
    "quantile_spread": 0.01267369207272958,
    "lowest_bucket_avg_return_pct": 0.0011093680935691408,
    "highest_bucket_avg_return_pct": -0.009134359279863901,
    "lowest_bucket_win_rate": 0.5126582278481012,
    "highest_bucket_win_rate": 0.3924050632911392,
    "usable_for_strategy_research": true,
    "reason": "candidate_research_only"
  },
  {
    "timeframe": "5m",
    "horizon": 6,
    "source_group": "agg_trade_pressure",
    "feature": "quote_volume_intensity",
    "sample_size": 158,
    "correlation": 0.08778821381381718,
    "abs_correlation": 0.08778821381381718,
    "quantile_spread": 0.09771524375840608,
    "lowest_bucket_avg_return_pct": 0.0130974496159489,
    "highest_bucket_avg_return_pct": 0.018553831958694963,
    "lowest_bucket_win_rate": 0.6774193548387096,
    "highest_bucket_win_rate": 0.53125,
    "usable_for_strategy_research": true,
    "reason": "candidate_research_only"
  },
  {
    "timeframe": "5m",
    "horizon": 3,
    "source_group": "agg_trade_pressure",
    "feature": "taker_net_base_volume",
    "sample_size": 158,
    "correlation": -0.08668959496701807,
    "abs_correlation": 0.08668959496701807,
    "quantile_spread": 0.055820876820865256,
    "lowest_bucket_avg_return_pct": 0.01752171496924641,
    "highest_bucket_avg_return_pct": -0.03829916185161884,
    "lowest_bucket_win_rate": 0.5483870967741935,
    "highest_bucket_win_rate": 0.28125,
    "usable_for_strategy_research": true,
    "reason": "candidate_research_only"
  },
  {
    "timeframe": "5m",
    "horizon": 3,
    "source_group": "agg_trade_pressure",
    "feature": "taker_net_quote_volume",
    "sample_size": 158,
    "correlation": -0.08665241331688797,
    "abs_correlation": 0.08665241331688797,
    "quantile_spread": 0.051622196417375296,
    "lowest_bucket_avg_return_pct": 0.01752171496924641,
    "highest_bucket_avg_return_pct": -0.03410048144812889,
    "lowest_bucket_win_rate": 0.5483870967741935,
    "highest_bucket_win_rate": 0.3125,
    "usable_for_strategy_research": true,
    "reason": "candidate_research_only"
  },
  {
    "timeframe": "1m",
    "horizon": 3,
    "source_group": "live_order_book",
    "feature": "imbalance_top_5",
    "sample_size": 216,
    "correlation": 0.08566671577209974,
    "abs_correlation": 0.08566671577209974,
    "quantile_spread": 0.03520670172129383,
    "lowest_bucket_avg_return_pct": -0.0016918115802788613,
    "highest_bucket_avg_return_pct": 0.03351489014101497,
    "lowest_bucket_win_rate": 0.5116279069767442,
    "highest_bucket_win_rate": 0.5227272727272727,
    "usable_for_strategy_research": true,
    "reason": "candidate_research_only"
  },
  {
    "timeframe": "1m",
    "horizon": 6,
    "source_group": "agg_trade_pressure",
    "feature": "taker_net_quote_volume",
    "sample_size": 790,
    "correlation": -0.0843253729651097,
    "abs_correlation": 0.0843253729651097,
    "quantile_spread": 0.02446181922259983,
    "lowest_bucket_avg_return_pct": 0.005822211624966588,
    "highest_bucket_avg_return_pct": -0.01863960759763324,
    "lowest_bucket_win_rate": 0.5379746835443038,
    "highest_bucket_win_rate": 0.3860759493670886,
    "usable_for_strategy_research": true,
    "reason": "candidate_research_only"
  },
  {
    "timeframe": "1m",
    "horizon": 6,
    "source_group": "agg_trade_pressure",
    "feature": "taker_net_base_volume",
    "sample_size": 790,
    "correlation": -0.08420174048631703,
    "abs_correlation": 0.08420174048631703,
    "quantile_spread": 0.02446181922259983,
    "lowest_bucket_avg_return_pct": 0.005822211624966588,
    "highest_bucket_avg_return_pct": -0.01863960759763324,
    "lowest_bucket_win_rate": 0.5379746835443038,
    "highest_bucket_win_rate": 0.3860759493670886,
    "usable_for_strategy_research": true,
    "reason": "candidate_research_only"
  },
  {
    "timeframe": "1m",
    "horizon": 6,
    "source_group": "agg_trade_pressure",
    "feature": "taker_buy_trade_ratio",
    "sample_size": 790,
    "correlation": -0.08410770432870066,
    "abs_correlation": 0.08410770432870066,
    "quantile_spread": 0.015856012094045968,
    "lowest_bucket_avg_return_pct": 0.005995041005423079,
    "highest_bucket_avg_return_pct": -0.009860971088622888,
    "lowest_bucket_win_rate": 0.5379746835443038,
    "highest_bucket_win_rate": 0.4936708860759494,
    "usable_for_strategy_research": true,
    "reason": "candidate_research_only"
  },
  {
    "timeframe": "1m",
    "horizon": 3,
    "source_group": "live_order_book",
    "feature": "order_book_imbalance",
    "sample_size": 216,
    "correlation": 0.08219755142592718,
    "abs_correlation": 0.08219755142592718,
    "quantile_spread": 0.056566799436389106,
    "lowest_bucket_avg_return_pct": 0.00011374975625242478,
    "highest_bucket_avg_return_pct": 0.03880992386794256,
    "lowest_bucket_win_rate": 0.5348837209302325,
    "highest_bucket_win_rate": 0.5227272727272727,
    "usable_for_strategy_research": true,
    "reason": "candidate_research_only"
  },
  {
    "timeframe": "1m",
    "horizon": 3,
    "source_group": "live_order_book",
    "feature": "imbalance_top_10",
    "sample_size": 216,
    "correlation": 0.08219755142592718,
    "abs_correlation": 0.08219755142592718,
    "quantile_spread": 0.056566799436389106,
    "lowest_bucket_avg_return_pct": 0.00011374975625242478,
    "highest_bucket_avg_return_pct": 0.03880992386794256,
    "lowest_bucket_win_rate": 0.5348837209302325,
    "highest_bucket_win_rate": 0.5227272727272727,
    "usable_for_strategy_research": true,
    "reason": "candidate_research_only"
  },
  {
    "timeframe": "1m",
    "horizon": 1,
    "source_group": "agg_trade_pressure",
    "feature": "taker_buy_base_ratio_trades",
    "sample_size": 790,
    "correlation": -0.08052675049291555,
    "abs_correlation": 0.08052675049291555,
    "quantile_spread": 0.01063806382337039,
    "lowest_bucket_avg_return_pct": 0.004745051392764315,
    "highest_bucket_avg_return_pct": -0.0058930124306060755,
    "lowest_bucket_win_rate": 0.5443037974683544,
    "highest_bucket_win_rate": 0.4430379746835443,
    "usable_for_strategy_research": true,
    "reason": "candidate_research_only"
  },
  {
    "timeframe": "1m",
    "horizon": 1,
    "source_group": "agg_trade_pressure",
    "feature": "taker_buy_quote_ratio_trades",
    "sample_size": 790,
    "correlation": -0.08052507035042186,
    "abs_correlation": 0.08052507035042186,
    "quantile_spread": 0.01063806382337039,
    "lowest_bucket_avg_return_pct": 0.004745051392764315,
    "highest_bucket_avg_return_pct": -0.0058930124306060755,
    "lowest_bucket_win_rate": 0.5443037974683544,
    "highest_bucket_win_rate": 0.4430379746835443,
    "usable_for_strategy_research": true,
    "reason": "candidate_research_only"
  },
  {
    "timeframe": "5m",
    "horizon": 1,
    "source_group": "agg_trade_pressure",
    "feature": "taker_buy_trade_ratio",
    "sample_size": 158,
    "correlation": -0.07608055611556465,
    "abs_correlation": 0.07608055611556465,
    "quantile_spread": 0.049354543151217595,
    "lowest_bucket_avg_return_pct": 0.006322404414384341,
    "highest_bucket_avg_return_pct": 0.005820133173595787,
    "lowest_bucket_win_rate": 0.6129032258064516,
    "highest_bucket_win_rate": 0.59375,
    "usable_for_strategy_research": true,
    "reason": "candidate_research_only"
  },
  {
    "timeframe": "5m",
    "horizon": 3,
    "source_group": "agg_trade_pressure",
    "feature": "quote_volume_intensity",
    "sample_size": 158,
    "correlation": 0.0722364043018735,
    "abs_correlation": 0.0722364043018735,
    "quantile_spread": 0.07891610133215446,
    "lowest_bucket_avg_return_pct": 0.010496617985060387,
    "highest_bucket_avg_return_pct": 0.02622708854460502,
    "lowest_bucket_win_rate": 0.6129032258064516,
    "highest_bucket_win_rate": 0.59375,
    "usable_for_strategy_research": true,
    "reason": "candidate_research_only"
  },
  {
    "timeframe": "1m",
    "horizon": 1,
    "source_group": "live_order_book",
    "feature": "imbalance_top_5",
    "sample_size": 216,
    "correlation": 0.0667677670304663,
    "abs_correlation": 0.0667677670304663,
    "quantile_spread": 0.030446102134815068,
    "lowest_bucket_avg_return_pct": -0.006739318070400979,
    "highest_bucket_avg_return_pct": 0.010993407925392511,
    "lowest_bucket_win_rate": 0.5348837209302325,
    "highest_bucket_win_rate": 0.5227272727272727,
    "usable_for_strategy_research": true,
    "reason": "candidate_research_only"
  },
  {
    "timeframe": "1m",
    "horizon": 1,
    "source_group": "agg_trade_pressure",
    "feature": "taker_buy_trade_ratio",
    "sample_size": 790,
    "correlation": -0.06637280411489402,
    "abs_correlation": 0.06637280411489402,
    "quantile_spread": 0.00993437784456241,
    "lowest_bucket_avg_return_pct": 0.001685655754880951,
    "highest_bucket_avg_return_pct": -0.003351738000170214,
    "lowest_bucket_win_rate": 0.4936708860759494,
    "highest_bucket_win_rate": 0.5063291139240507,
    "usable_for_strategy_research": true,
    "reason": "candidate_research_only"
  },
  {
    "timeframe": "1m",
    "horizon": 3,
    "source_group": "live_order_book",
    "feature": "imbalance_top_20",
    "sample_size": 216,
    "correlation": 0.06538525449464616,
    "abs_correlation": 0.06538525449464616,
    "quantile_spread": 0.05459918064151815,
    "lowest_bucket_avg_return_pct": 0.008217609374653477,
    "highest_bucket_avg_return_pct": 0.03590772361771844,
    "lowest_bucket_win_rate": 0.5348837209302325,
    "highest_bucket_win_rate": 0.5454545454545454,
    "usable_for_strategy_research": true,
    "reason": "candidate_research_only"
  },
  {
    "timeframe": "1m",
    "horizon": 1,
    "source_group": "agg_trade_pressure",
    "feature": "trade_count_intensity",
    "sample_size": 790,
    "correlation": -0.06309854742065049,
    "abs_correlation": 0.06309854742065049,
    "quantile_spread": 0.007549512574344183,
    "lowest_bucket_avg_return_pct": -0.0004659017465848567,
    "highest_bucket_avg_return_pct": -0.001329106549903642,
    "lowest_bucket_win_rate": 0.4810126582278481,
    "highest_bucket_win_rate": 0.5126582278481012,
    "usable_for_strategy_research": true,
    "reason": "candidate_research_only"
  },
  {
    "timeframe": "1m",
    "horizon": 1,
    "source_group": "live_order_book",
    "feature": "order_book_imbalance",
    "sample_size": 216,
    "correlation": 0.059685874259677196,
    "abs_correlation": 0.059685874259677196,
    "quantile_spread": 0.02768309084540399,
    "lowest_bucket_avg_return_pct": -0.008254903139835448,
    "highest_bucket_avg_return_pct": 0.01942818770556854,
    "lowest_bucket_win_rate": 0.5348837209302325,
    "highest_bucket_win_rate": 0.5227272727272727,
    "usable_for_strategy_research": true,
    "reason": "candidate_research_only"
  },
  {
    "timeframe": "1m",
    "horizon": 1,
    "source_group": "live_order_book",
    "feature": "imbalance_top_10",
    "sample_size": 216,
    "correlation": 0.059685874259677196,
    "abs_correlation": 0.059685874259677196,
    "quantile_spread": 0.02768309084540399,
    "lowest_bucket_avg_return_pct": -0.008254903139835448,
    "highest_bucket_avg_return_pct": 0.01942818770556854,
    "lowest_bucket_win_rate": 0.5348837209302325,
    "highest_bucket_win_rate": 0.5227272727272727,
    "usable_for_strategy_research": true,
    "reason": "candidate_research_only"
  },
  {
    "timeframe": "15m",
    "horizon": 6,
    "source_group": "candle_only",
    "feature": "lower_wick_pct",
    "sample_size": 3325,
    "correlation": 0.05069639263795576,
    "abs_correlation": 0.05069639263795576,
    "quantile_spread": 0.04643746120203088,
    "lowest_bucket_avg_return_pct": -0.03108837361050832,
    "highest_bucket_avg_return_pct": -0.057536776752998446,
    "lowest_bucket_win_rate": 0.46466165413533833,
    "highest_bucket_win_rate": 0.45112781954887216,
    "usable_for_strategy_research": true,
    "reason": "candidate_research_only"
  },
  {
    "timeframe": "5m",
    "horizon": 1,
    "source_group": "agg_trade_pressure",
    "feature": "avg_trade_quote_size",
    "sample_size": 158,
    "correlation": 0.049543909334665584,
    "abs_correlation": 0.049543909334665584,
    "quantile_spread": 0.04400675408446983,
    "lowest_bucket_avg_return_pct": 0.00011158537253561857,
    "highest_bucket_avg_return_pct": 0.01341342146751468,
    "lowest_bucket_win_rate": 0.5161290322580645,
    "highest_bucket_win_rate": 0.65625,
    "usable_for_strategy_research": true,
    "reason": "candidate_research_only"
  },
  {
    "timeframe": "15m",
    "horizon": 6,
    "source_group": "candle_only",
    "feature": "volume_spike_ratio",
    "sample_size": 3305,
    "correlation": 0.04876052947330109,
    "abs_correlation": 0.04876052947330109,
    "quantile_spread": 0.1384365719406417,
    "lowest_bucket_avg_return_pct": -0.13504087173954316,
    "highest_bucket_avg_return_pct": 0.0033957002010985586,
    "lowest_bucket_win_rate": 0.3888048411497731,
    "highest_bucket_win_rate": 0.491679273827534,
    "usable_for_strategy_research": true,
    "reason": "candidate_research_only"
  },
  {
    "timeframe": "5m",
    "horizon": 3,
    "source_group": "candle_only",
    "feature": "upper_wick_pct",
    "sample_size": 9995,
    "correlation": 0.047977534213321946,
    "abs_correlation": 0.047977534213321946,
    "quantile_spread": 0.02099103587497446,
    "lowest_bucket_avg_return_pct": -0.006550312175087524,
    "highest_bucket_avg_return_pct": 0.007652369461725593,
    "lowest_bucket_win_rate": 0.4737368684342171,
    "highest_bucket_win_rate": 0.5192596298149075,
    "usable_for_strategy_research": true,
    "reason": "candidate_research_only"
  },
  {
    "timeframe": "15m",
    "horizon": 6,
    "source_group": "candle_only",
    "feature": "upper_wick_pct",
    "sample_size": 3325,
    "correlation": 0.040334629883689604,
    "abs_correlation": 0.040334629883689604,
    "quantile_spread": 0.05944888499639745,
    "lowest_bucket_avg_return_pct": -0.07334215609953737,
    "highest_bucket_avg_return_pct": -0.026002005544726856,
    "lowest_bucket_win_rate": 0.44661654135338347,
    "highest_bucket_win_rate": 0.46616541353383456,
    "usable_for_strategy_research": true,
    "reason": "candidate_research_only"
  },
  {
    "timeframe": "5m",
    "horizon": 6,
    "source_group": "candle_only",
    "feature": "upper_wick_pct",
    "sample_size": 9992,
    "correlation": 0.03668351557023195,
    "abs_correlation": 0.03668351557023195,
    "quantile_spread": 0.029716497751342205,
    "lowest_bucket_avg_return_pct": -0.012772764262963253,
    "highest_bucket_avg_return_pct": 0.003831137947098041,
    "lowest_bucket_win_rate": 0.4914914914914915,
    "highest_bucket_win_rate": 0.5087543771885943,
    "usable_for_strategy_research": true,
    "reason": "candidate_research_only"
  },
  {
    "timeframe": "15m",
    "horizon": 3,
    "source_group": "candle_only",
    "feature": "body_pct",
    "sample_size": 3328,
    "correlation": 0.03618752414969302,
    "abs_correlation": 0.03618752414969302,
    "quantile_spread": 0.03239354618274129,
    "lowest_bucket_avg_return_pct": -0.012150059327994775,
    "highest_bucket_avg_return_pct": -0.0006407982232133943,
    "lowest_bucket_win_rate": 0.4917293233082707,
    "highest_bucket_win_rate": 0.47597597597597596,
    "usable_for_strategy_research": true,
    "reason": "candidate_research_only"
  },
  {
    "timeframe": "15m",
    "horizon": 3,
    "source_group": "candle_only",
    "feature": "lower_wick_pct",
    "sample_size": 3328,
    "correlation": 0.030969827095501636,
    "abs_correlation": 0.030969827095501636,
    "quantile_spread": 0.031802258839599674,
    "lowest_bucket_avg_return_pct": -0.014847575293506575,
    "highest_bucket_avg_return_pct": -0.037268358849079024,
    "lowest_bucket_win_rate": 0.49022556390977445,
    "highest_bucket_win_rate": 0.46546546546546547,
    "usable_for_strategy_research": true,
    "reason": "candidate_research_only"
  },
  {
    "timeframe": "5m",
    "horizon": 1,
    "source_group": "agg_trade_pressure",
    "feature": "quote_volume_intensity",
    "sample_size": 158,
    "correlation": 0.028926592633872414,
    "abs_correlation": 0.028926592633872414,
    "quantile_spread": 0.037893386291680264,
    "lowest_bucket_avg_return_pct": 0.005635619229688037,
    "highest_bucket_avg_return_pct": 0.015822349890171884,
    "lowest_bucket_win_rate": 0.6129032258064516,
    "highest_bucket_win_rate": 0.65625,
    "usable_for_strategy_research": true,
    "reason": "candidate_research_only"
  },
  {
    "timeframe": "15m",
    "horizon": 6,
    "source_group": "candle_only",
    "feature": "body_pct",
    "sample_size": 3325,
    "correlation": 0.02803444290593111,
    "abs_correlation": 0.02803444290593111,
    "quantile_spread": 0.05995063447507497,
    "lowest_bucket_avg_return_pct": -0.030997743959419878,
    "highest_bucket_avg_return_pct": -0.020185450598820834,
    "lowest_bucket_win_rate": 0.4766917293233083,
    "highest_bucket_win_rate": 0.48270676691729325,
    "usable_for_strategy_research": true,
    "reason": "candidate_research_only"
  },
  {
    "timeframe": "1m",
    "horizon": 1,
    "source_group": "live_order_book",
    "feature": "spread_pct",
    "sample_size": 216,
    "correlation": 0.025016422162702057,
    "abs_correlation": 0.025016422162702057,
    "quantile_spread": 0.045679525937084346,
    "lowest_bucket_avg_return_pct": 0.0004508733195205525,
    "highest_bucket_avg_return_pct": 0.02159742554998455,
    "lowest_bucket_win_rate": 0.5348837209302325,
    "highest_bucket_win_rate": 0.6590909090909091,
    "usable_for_strategy_research": true,
    "reason": "candidate_research_only"
  },
  {
    "timeframe": "5m",
    "horizon": 3,
    "source_group": "agg_trade_pressure",
    "feature": "trade_count_intensity",
    "sample_size": 158,
    "correlation": -0.022021221077608937,
    "abs_correlation": 0.022021221077608937,
    "quantile_spread": 0.049194512229939175,
    "lowest_bucket_avg_return_pct": -0.003314099216061865,
    "highest_bucket_avg_return_pct": -0.0166126091777748,
    "lowest_bucket_win_rate": 0.5483870967741935,
    "highest_bucket_win_rate": 0.40625,
    "usable_for_strategy_research": true,
    "reason": "candidate_research_only"
  },
  {
    "timeframe": "15m",
    "horizon": 3,
    "source_group": "kline_taker",
    "feature": "taker_buy_ratio",
    "sample_size": 3262,
    "correlation": -0.021549893418291687,
    "abs_correlation": 0.021549893418291687,
    "quantile_spread": 0.03205927636420144,
    "lowest_bucket_avg_return_pct": -0.005856695767851367,
    "highest_bucket_avg_return_pct": -0.027095778681996013,
    "lowest_bucket_win_rate": 0.495398773006135,
    "highest_bucket_win_rate": 0.46248085758039814,
    "usable_for_strategy_research": true,
    "reason": "candidate_research_only"
  },
  {
    "timeframe": "5m",
    "horizon": 6,
    "source_group": "candle_only",
    "feature": "lower_wick_pct",
    "sample_size": 9992,
    "correlation": -0.019338755613142685,
    "abs_correlation": 0.019338755613142685,
    "quantile_spread": 0.020690842773223746,
    "lowest_bucket_avg_return_pct": -0.003896407116165586,
    "highest_bucket_avg_return_pct": -0.013339575235377014,
    "lowest_bucket_win_rate": 0.498998998998999,
    "highest_bucket_win_rate": 0.4897448724362181,
    "usable_for_strategy_research": true,
    "reason": "candidate_research_only"
  },
  {
    "timeframe": "5m",
    "horizon": 6,
    "source_group": "kline_taker",
    "feature": "taker_buy_ratio",
    "sample_size": 9798,
    "correlation": -0.017716585147446135,
    "abs_correlation": 0.017716585147446135,
    "quantile_spread": 0.031069867540503195,
    "lowest_bucket_avg_return_pct": -0.01069514053990845,
    "highest_bucket_avg_return_pct": -0.02123955587448684,
    "lowest_bucket_win_rate": 0.5119959162838182,
    "highest_bucket_win_rate": 0.45714285714285713,
    "usable_for_strategy_research": true,
    "reason": "candidate_research_only"
  },
  {
    "timeframe": "15m",
    "horizon": 1,
    "source_group": "kline_taker",
    "feature": "taker_buy_ratio",
    "sample_size": 3264,
    "correlation": -0.01744076126111385,
    "abs_correlation": 0.01744076126111385,
    "quantile_spread": 0.020382949427406503,
    "lowest_bucket_avg_return_pct": -0.005642383582596016,
    "highest_bucket_avg_return_pct": -0.018171802088733608,
    "lowest_bucket_win_rate": 0.49846625766871167,
    "highest_bucket_win_rate": 0.43644716692189894,
    "usable_for_strategy_research": true,
    "reason": "candidate_research_only"
  },
  {
    "timeframe": "5m",
    "horizon": 3,
    "source_group": "agg_trade_pressure",
    "feature": "taker_buy_trade_ratio",
    "sample_size": 158,
    "correlation": -0.015020972517932853,
    "abs_correlation": 0.015020972517932853,
    "quantile_spread": 0.09316122996423315,
    "lowest_bucket_avg_return_pct": -0.0025080724627282087,
    "highest_bucket_avg_return_pct": -0.006726217873093073,
    "lowest_bucket_win_rate": 0.5161290322580645,
    "highest_bucket_win_rate": 0.5,
    "usable_for_strategy_research": true,
    "reason": "candidate_research_only"
  },
  {
    "timeframe": "1m",
    "horizon": 6,
    "source_group": "live_order_book",
    "feature": "spread_pct",
    "sample_size": 216,
    "correlation": -0.014696084419874921,
    "abs_correlation": 0.014696084419874921,
    "quantile_spread": 0.17495316998129629,
    "lowest_bucket_avg_return_pct": 0.04892185739131212,
    "highest_bucket_avg_return_pct": 0.051675623089309404,
    "lowest_bucket_win_rate": 0.46511627906976744,
    "highest_bucket_win_rate": 0.75,
    "usable_for_strategy_research": true,
    "reason": "candidate_research_only"
  },
  {
    "timeframe": "1m",
    "horizon": 1,
    "source_group": "live_order_book",
    "feature": "imbalance_top_20",
    "sample_size": 216,
    "correlation": 0.011671848731043807,
    "abs_correlation": 0.011671848731043807,
    "quantile_spread": 0.023991288735482764,
    "lowest_bucket_avg_return_pct": 0.00912631618717176,
    "highest_bucket_avg_return_pct": 0.015295754857500166,
    "lowest_bucket_win_rate": 0.627906976744186,
    "highest_bucket_win_rate": 0.5227272727272727,
    "usable_for_strategy_research": true,
    "reason": "candidate_research_only"
  },
  {
    "timeframe": "5m",
    "horizon": 6,
    "source_group": "agg_trade_pressure",
    "feature": "trade_count_intensity",
    "sample_size": 158,
    "correlation": -0.011415099498079364,
    "abs_correlation": 0.011415099498079364,
    "quantile_spread": 0.08771666413005112,
    "lowest_bucket_avg_return_pct": -0.007054315182726006,
    "highest_bucket_avg_return_pct": -0.015929281491319496,
    "lowest_bucket_win_rate": 0.45161290322580644,
    "highest_bucket_win_rate": 0.46875,
    "usable_for_strategy_research": true,
    "reason": "candidate_research_only"
  },
  {
    "timeframe": "15m",
    "horizon": 6,
    "source_group": "kline_taker",
    "feature": "taker_buy_ratio",
    "sample_size": 3259,
    "correlation": -0.009612055015845559,
    "abs_correlation": 0.009612055015845559,
    "quantile_spread": 0.05456554132546677,
    "lowest_bucket_avg_return_pct": -0.03821012985553864,
    "highest_bucket_avg_return_pct": -0.04523785072478004,
    "lowest_bucket_win_rate": 0.45622119815668205,
    "highest_bucket_win_rate": 0.4677914110429448,
    "usable_for_strategy_research": true,
    "reason": "candidate_research_only"
  },
  {
    "timeframe": "15m",
    "horizon": 3,
    "source_group": "candle_only",
    "feature": "volume_spike_ratio",
    "sample_size": 3308,
    "correlation": 0.006557892586763213,
    "abs_correlation": 0.006557892586763213,
    "quantile_spread": 0.06630230015056363,
    "lowest_bucket_avg_return_pct": -0.0668244467597872,
    "highest_bucket_avg_return_pct": -0.011006129782065692,
    "lowest_bucket_win_rate": 0.43116490166414523,
    "highest_bucket_win_rate": 0.49697885196374625,
    "usable_for_strategy_research": true,
    "reason": "candidate_research_only"
  },
  {
    "timeframe": "15m",
    "horizon": 1,
    "source_group": "candle_only",
    "feature": "lower_wick_pct",
    "sample_size": 3330,
    "correlation": 0.005559165687121149,
    "abs_correlation": 0.005559165687121149,
    "quantile_spread": 0.031449021379644546,
    "lowest_bucket_avg_return_pct": -0.0038827976323729274,
    "highest_bucket_avg_return_pct": -0.024739752797974912,
    "lowest_bucket_win_rate": 0.4924924924924925,
    "highest_bucket_win_rate": 0.4369369369369369,
    "usable_for_strategy_research": true,
    "reason": "candidate_research_only"
  },
  {
    "timeframe": "15m",
    "horizon": 1,
    "source_group": "candle_only",
    "feature": "volume_spike_ratio",
    "sample_size": 3310,
    "correlation": 0.0026530145794035676,
    "abs_correlation": 0.0026530145794035676,
    "quantile_spread": 0.03242577730398119,
    "lowest_bucket_avg_return_pct": -0.021590538470517392,
    "highest_bucket_avg_return_pct": -0.005440316645015263,
    "lowest_bucket_win_rate": 0.46827794561933533,
    "highest_bucket_win_rate": 0.4637462235649547,
    "usable_for_strategy_research": true,
    "reason": "candidate_research_only"
  },
  {
    "timeframe": "5m",
    "horizon": 6,
    "source_group": "agg_trade_pressure",
    "feature": "taker_buy_trade_ratio",
    "sample_size": 158,
    "correlation": 0.0016124165127343107,
    "abs_correlation": 0.0016124165127343107,
    "quantile_spread": 0.05206305475904496,
    "lowest_bucket_avg_return_pct": -0.009723714587011816,
    "highest_bucket_avg_return_pct": -0.01899106324670367,
    "lowest_bucket_win_rate": 0.45161290322580644,
    "highest_bucket_win_rate": 0.46875,
    "usable_for_strategy_research": true,
    "reason": "candidate_research_only"
  },
  {
    "timeframe": "1m",
    "horizon": 3,
    "source_group": "live_order_book",
    "feature": "spread_pct",
    "sample_size": 216,
    "correlation": 0.0016115181085397836,
    "abs_correlation": 0.0016115181085397836,
    "quantile_spread": 0.09765448867556796,
    "lowest_bucket_avg_return_pct": 0.030544961721310195,
    "highest_bucket_avg_return_pct": 0.03957503778414795,
    "lowest_bucket_win_rate": 0.4186046511627907,
    "highest_bucket_win_rate": 0.6363636363636364,
    "usable_for_strategy_research": true,
    "reason": "candidate_research_only"
  },
  {
    "timeframe": "5m",
    "horizon": 1,
    "source_group": "agg_trade_pressure",
    "feature": "trade_count_intensity",
    "sample_size": 158,
    "correlation": -0.0009394015038765036,
    "abs_correlation": 0.0009394015038765036,
    "quantile_spread": 0.027279482267594843,
    "lowest_bucket_avg_return_pct": -0.004726152627413839,
    "highest_bucket_avg_return_pct": -0.01133936816037319,
    "lowest_bucket_win_rate": 0.45161290322580644,
    "highest_bucket_win_rate": 0.5,
    "usable_for_strategy_research": true,
    "reason": "candidate_research_only"
  },
  {
    "timeframe": "1m",
    "horizon": 6,
    "source_group": "agg_trade_pressure",
    "feature": "trade_count_intensity",
    "sample_size": 790,
    "correlation": -0.00040295619629310443,
    "abs_correlation": 0.00040295619629310443,
    "quantile_spread": 0.022211242325042256,
    "lowest_bucket_avg_return_pct": -0.005360901769631843,
    "highest_bucket_avg_return_pct": -0.006745867809068409,
    "lowest_bucket_win_rate": 0.5253164556962026,
    "highest_bucket_win_rate": 0.45569620253164556,
    "usable_for_strategy_research": true,
    "reason": "candidate_research_only"
  },
  {
    "timeframe": "15m",
    "horizon": 3,
    "source_group": "candle_only",
    "feature": "upper_wick_pct",
    "sample_size": 3328,
    "correlation": -9.99906703095182e-05,
    "abs_correlation": 9.99906703095182e-05,
    "quantile_spread": 0.0314933543583423,
    "lowest_bucket_avg_return_pct": -0.022894611411921877,
    "highest_bucket_avg_return_pct": -0.03314581972578624,
    "lowest_bucket_win_rate": 0.5067669172932331,
    "highest_bucket_win_rate": 0.45645645645645644,
    "usable_for_strategy_research": true,
    "reason": "candidate_research_only"
  },
  {
    "timeframe": "5m",
    "horizon": 1,
    "source_group": "candle_only",
    "feature": "upper_wick_pct",
    "sample_size": 9997,
    "correlation": 0.04221932827525408,
    "abs_correlation": 0.04221932827525408,
    "quantile_spread": 0.010807527540495855,
    "lowest_bucket_avg_return_pct": -0.005570358036456631,
    "highest_bucket_avg_return_pct": 0.005237169504039224,
    "lowest_bucket_win_rate": 0.47573786893446723,
    "highest_bucket_win_rate": 0.513,
    "usable_for_strategy_research": true,
    "reason": "weak_signal"
  },
  {
    "timeframe": "5m",
    "horizon": 3,
    "source_group": "candle_only",
    "feature": "lower_wick_pct",
    "sample_size": 9995,
    "correlation": -0.03780685943537006,
    "abs_correlation": 0.03780685943537006,
    "quantile_spread": 0.011836752955037647,
    "lowest_bucket_avg_return_pct": 0.00076505158693479,
    "highest_bucket_avg_return_pct": -0.011071701368102857,
    "lowest_bucket_win_rate": 0.5182591295647824,
    "highest_bucket_win_rate": 0.4812406203101551,
    "usable_for_strategy_research": true,
    "reason": "weak_signal"
  },
  {
    "timeframe": "5m",
    "horizon": 6,
    "source_group": "candle_only",
    "feature": "body_pct",
    "sample_size": 9992,
    "correlation": 0.03335228651835322,
    "abs_correlation": 0.03335228651835322,
    "quantile_spread": 0.017909111185924927,
    "lowest_bucket_avg_return_pct": -0.006118497007411513,
    "highest_bucket_avg_return_pct": -0.007357707640259428,
    "lowest_bucket_win_rate": 0.5095095095095095,
    "highest_bucket_win_rate": 0.4882441220610305,
    "usable_for_strategy_research": true,
    "reason": "weak_signal"
  },
  {
    "timeframe": "1m",
    "horizon": 1,
    "source_group": "agg_trade_pressure",
    "feature": "quote_volume_intensity",
    "sample_size": 790,
    "correlation": -0.03296482630746298,
    "abs_correlation": 0.03296482630746298,
    "quantile_spread": 0.00876721509210502,
    "lowest_bucket_avg_return_pct": 0.0011294860487916561,
    "highest_bucket_avg_return_pct": -0.004444878154333244,
    "lowest_bucket_win_rate": 0.5126582278481012,
    "highest_bucket_win_rate": 0.4620253164556962,
    "usable_for_strategy_research": true,
    "reason": "weak_signal"
  },
  {
    "timeframe": "1m",
    "horizon": 6,
    "source_group": "candle_only",
    "feature": "body_pct",
    "sample_size": 49994,
    "correlation": 0.026493985935064447,
    "abs_correlation": 0.026493985935064447,
    "quantile_spread": 0.008063549483599445,
    "lowest_bucket_avg_return_pct": -0.00150379823508378,
    "highest_bucket_avg_return_pct": 0.0012565642857745299,
    "lowest_bucket_win_rate": 0.4916983396679336,
    "highest_bucket_win_rate": 0.4963496349634963,
    "usable_for_strategy_research": true,
    "reason": "weak_signal"
  },
  {
    "timeframe": "1m",
    "horizon": 6,
    "source_group": "agg_trade_pressure",
    "feature": "avg_trade_quote_size",
    "sample_size": 790,
    "correlation": 0.024493565670368478,
    "abs_correlation": 0.024493565670368478,
    "quantile_spread": 0.00884632041242665,
    "lowest_bucket_avg_return_pct": 0.001571052676093822,
    "highest_bucket_avg_return_pct": -0.007275267736332827,
    "lowest_bucket_win_rate": 0.5443037974683544,
    "highest_bucket_win_rate": 0.44936708860759494,
    "usable_for_strategy_research": true,
    "reason": "weak_signal"
  },
  {
    "timeframe": "1m",
    "horizon": 1,
    "source_group": "candle_only",
    "feature": "body_pct",
    "sample_size": 49999,
    "correlation": 0.024429020419436644,
    "abs_correlation": 0.024429020419436644,
    "quantile_spread": 0.0015012152597331959,
    "lowest_bucket_avg_return_pct": 0.00035466255021473044,
    "highest_bucket_avg_return_pct": -0.000440760890429799,
    "lowest_bucket_win_rate": 0.4746474647464746,
    "highest_bucket_win_rate": 0.4862,
    "usable_for_strategy_research": true,
    "reason": "weak_signal"
  },
  {
    "timeframe": "1m",
    "horizon": 6,
    "source_group": "agg_trade_pressure",
    "feature": "quote_volume_intensity",
    "sample_size": 790,
    "correlation": 0.022294674261004382,
    "abs_correlation": 0.022294674261004382,
    "quantile_spread": 0.01948933265428647,
    "lowest_bucket_avg_return_pct": -0.004699902223521614,
    "highest_bucket_avg_return_pct": -0.007256493801018041,
    "lowest_bucket_win_rate": 0.5189873417721519,
    "highest_bucket_win_rate": 0.44936708860759494,
    "usable_for_strategy_research": true,
    "reason": "weak_signal"
  },
  {
    "timeframe": "1m",
    "horizon": 3,
    "source_group": "candle_only",
    "feature": "body_pct",
    "sample_size": 49997,
    "correlation": 0.022118390750007946,
    "abs_correlation": 0.022118390750007946,
    "quantile_spread": 0.003085890169015185,
    "lowest_bucket_avg_return_pct": 4.1418828470423505e-05,
    "highest_bucket_avg_return_pct": -0.00010203089589172521,
    "lowest_bucket_win_rate": 0.49544954495449545,
    "highest_bucket_win_rate": 0.4913,
    "usable_for_strategy_research": true,
    "reason": "weak_signal"
  },
  {
    "timeframe": "1m",
    "horizon": 6,
    "source_group": "candle_only",
    "feature": "lower_wick_pct",
    "sample_size": 49994,
    "correlation": 0.021613179441411095,
    "abs_correlation": 0.021613179441411095,
    "quantile_spread": 0.005875789800202824,
    "lowest_bucket_avg_return_pct": -0.003414251544332732,
    "highest_bucket_avg_return_pct": -0.00033820910175844804,
    "lowest_bucket_win_rate": 0.48899779955991196,
    "highest_bucket_win_rate": 0.49424942494249424,
    "usable_for_strategy_research": true,
    "reason": "weak_signal"
  },
  {
    "timeframe": "1m",
    "horizon": 3,
    "source_group": "candle_only",
    "feature": "lower_wick_pct",
    "sample_size": 49997,
    "correlation": 0.01940112297797385,
    "abs_correlation": 0.01940112297797385,
    "quantile_spread": 0.005394930334778743,
    "lowest_bucket_avg_return_pct": -0.003408861860408281,
    "highest_bucket_avg_return_pct": 0.00042049950440859883,
    "lowest_bucket_win_rate": 0.47954795479547957,
    "highest_bucket_win_rate": 0.4973,
    "usable_for_strategy_research": true,
    "reason": "weak_signal"
  },
  {
    "timeframe": "5m",
    "horizon": 3,
    "source_group": "kline_taker",
    "feature": "taker_buy_ratio",
    "sample_size": 9801,
    "correlation": -0.016604004153451455,
    "abs_correlation": 0.016604004153451455,
    "quantile_spread": 0.01661989775590737,
    "lowest_bucket_avg_return_pct": -0.005146884750780772,
    "highest_bucket_avg_return_pct": -0.012567360427169574,
    "lowest_bucket_win_rate": 0.5137755102040816,
    "highest_bucket_win_rate": 0.4599694033656298,
    "usable_for_strategy_research": true,
    "reason": "weak_signal"
  },
  {
    "timeframe": "15m",
    "horizon": 1,
    "source_group": "candle_only",
    "feature": "upper_wick_pct",
    "sample_size": 3330,
    "correlation": 0.016098241104159042,
    "abs_correlation": 0.016098241104159042,
    "quantile_spread": 0.007189341556081204,
    "lowest_bucket_avg_return_pct": -0.007578285659329906,
    "highest_bucket_avg_return_pct": -0.001993451197232073,
    "lowest_bucket_win_rate": 0.47147147147147145,
    "highest_bucket_win_rate": 0.48348348348348347,
    "usable_for_strategy_research": true,
    "reason": "weak_signal"
  },
  {
    "timeframe": "5m",
    "horizon": 3,
    "source_group": "candle_only",
    "feature": "body_pct",
    "sample_size": 9995,
    "correlation": 0.014661534630205933,
    "abs_correlation": 0.014661534630205933,
    "quantile_spread": 0.011073635164336564,
    "lowest_bucket_avg_return_pct": -0.001719347233263202,
    "highest_bucket_avg_return_pct": -0.0009079248960334669,
    "lowest_bucket_win_rate": 0.5102551275637819,
    "highest_bucket_win_rate": 0.47873936968484243,
    "usable_for_strategy_research": true,
    "reason": "weak_signal"
  },
  {
    "timeframe": "5m",
    "horizon": 1,
    "source_group": "kline_taker",
    "feature": "taker_buy_ratio",
    "sample_size": 9803,
    "correlation": -0.014300326129251332,
    "abs_correlation": 0.014300326129251332,
    "quantile_spread": 0.005289435345827841,
    "lowest_bucket_avg_return_pct": -0.00045514561827673114,
    "highest_bucket_avg_return_pct": -0.005744580964104571,
    "lowest_bucket_win_rate": 0.5209183673469387,
    "highest_bucket_win_rate": 0.46659867414584394,
    "usable_for_strategy_research": true,
    "reason": "weak_signal"
  },
  {
    "timeframe": "15m",
    "horizon": 1,
    "source_group": "candle_only",
    "feature": "body_pct",
    "sample_size": 3330,
    "correlation": 0.013250483023806681,
    "abs_correlation": 0.013250483023806681,
    "quantile_spread": 0.007488103946434621,
    "lowest_bucket_avg_return_pct": -0.006939215914781028,
    "highest_bucket_avg_return_pct": -0.010827191069292965,
    "lowest_bucket_win_rate": 0.5015015015015015,
    "highest_bucket_win_rate": 0.4924924924924925,
    "usable_for_strategy_research": true,
    "reason": "weak_signal"
  },
  {
    "timeframe": "1m",
    "horizon": 3,
    "source_group": "agg_trade_pressure",
    "feature": "trade_count_intensity",
    "sample_size": 790,
    "correlation": -0.012813241187550789,
    "abs_correlation": 0.012813241187550789,
    "quantile_spread": 0.018739809562707536,
    "lowest_bucket_avg_return_pct": -0.0008632387555296524,
    "highest_bucket_avg_return_pct": -0.003570595983855185,
    "lowest_bucket_win_rate": 0.46835443037974683,
    "highest_bucket_win_rate": 0.45569620253164556,
    "usable_for_strategy_research": true,
    "reason": "weak_signal"
  },
  {
    "timeframe": "1m",
    "horizon": 1,
    "source_group": "kline_taker",
    "feature": "taker_buy_ratio",
    "sample_size": 48631,
    "correlation": 0.012472796499472812,
    "abs_correlation": 0.012472796499472812,
    "quantile_spread": 0.002077539006727572,
    "lowest_bucket_avg_return_pct": -0.0014046962785940044,
    "highest_bucket_avg_return_pct": 0.0006728427281335675,
    "lowest_bucket_win_rate": 0.4809788196586469,
    "highest_bucket_win_rate": 0.4776395599876632,
    "usable_for_strategy_research": true,
    "reason": "weak_signal"
  },
  {
    "timeframe": "5m",
    "horizon": 3,
    "source_group": "candle_only",
    "feature": "volume_spike_ratio",
    "sample_size": 9975,
    "correlation": -0.012175377047685704,
    "abs_correlation": 0.012175377047685704,
    "quantile_spread": 0.0124178641128733,
    "lowest_bucket_avg_return_pct": -0.004470686046495918,
    "highest_bucket_avg_return_pct": -0.014361492456731602,
    "lowest_bucket_win_rate": 0.49022556390977445,
    "highest_bucket_win_rate": 0.47218045112781953,
    "usable_for_strategy_research": true,
    "reason": "weak_signal"
  },
  {
    "timeframe": "1m",
    "horizon": 1,
    "source_group": "candle_only",
    "feature": "lower_wick_pct",
    "sample_size": 49999,
    "correlation": 0.010107857613134525,
    "abs_correlation": 0.010107857613134525,
    "quantile_spread": 0.0030919501055905923,
    "lowest_bucket_avg_return_pct": -0.0018985124747316717,
    "highest_bucket_avg_return_pct": 0.0005557495175629493,
    "lowest_bucket_win_rate": 0.4675467546754675,
    "highest_bucket_win_rate": 0.499,
    "usable_for_strategy_research": true,
    "reason": "weak_signal"
  },
  {
    "timeframe": "1m",
    "horizon": 3,
    "source_group": "candle_only",
    "feature": "upper_wick_pct",
    "sample_size": 49997,
    "correlation": 0.0099224483112634,
    "abs_correlation": 0.0099224483112634,
    "quantile_spread": 0.0052541254806221255,
    "lowest_bucket_avg_return_pct": 0.0012998196982434871,
    "highest_bucket_avg_return_pct": -0.0027703854591348727,
    "lowest_bucket_win_rate": 0.5076507650765076,
    "highest_bucket_win_rate": 0.4818,
    "usable_for_strategy_research": true,
    "reason": "weak_signal"
  },
  {
    "timeframe": "1m",
    "horizon": 3,
    "source_group": "kline_taker",
    "feature": "taker_buy_ratio",
    "sample_size": 48629,
    "correlation": -0.008049544475843001,
    "abs_correlation": 0.008049544475843001,
    "quantile_spread": 0.004030733406437825,
    "lowest_bucket_avg_return_pct": -0.00044025929776210715,
    "highest_bucket_avg_return_pct": -0.0019985736972029794,
    "lowest_bucket_win_rate": 0.5051928020565553,
    "highest_bucket_win_rate": 0.47912811022002877,
    "usable_for_strategy_research": true,
    "reason": "weak_signal"
  },
  {
    "timeframe": "1m",
    "horizon": 3,
    "source_group": "candle_only",
    "feature": "volume_spike_ratio",
    "sample_size": 49977,
    "correlation": 0.007759681108392538,
    "abs_correlation": 0.007759681108392538,
    "quantile_spread": 0.003721925037674739,
    "lowest_bucket_avg_return_pct": -0.0004579877196584269,
    "highest_bucket_avg_return_pct": 0.0004478072017391757,
    "lowest_bucket_win_rate": 0.49864932466233114,
    "highest_bucket_win_rate": 0.4955982392957183,
    "usable_for_strategy_research": true,
    "reason": "weak_signal"
  },
  {
    "timeframe": "1m",
    "horizon": 6,
    "source_group": "candle_only",
    "feature": "volume_spike_ratio",
    "sample_size": 49974,
    "correlation": 0.007295563215639809,
    "abs_correlation": 0.007295563215639809,
    "quantile_spread": 0.0049571399257484485,
    "lowest_bucket_avg_return_pct": -0.0012078172298728258,
    "highest_bucket_avg_return_pct": -6.597126990006844e-05,
    "lowest_bucket_win_rate": 0.4990994596758055,
    "highest_bucket_win_rate": 0.4961480740370185,
    "usable_for_strategy_research": true,
    "reason": "weak_signal"
  },
  {
    "timeframe": "1m",
    "horizon": 6,
    "source_group": "kline_taker",
    "feature": "taker_buy_ratio",
    "sample_size": 48626,
    "correlation": -0.006384329783181266,
    "abs_correlation": 0.006384329783181266,
    "quantile_spread": 0.00409442049446216,
    "lowest_bucket_avg_return_pct": -0.0020224514217133953,
    "highest_bucket_avg_return_pct": -0.003638020302654553,
    "lowest_bucket_win_rate": 0.5109511568123394,
    "highest_bucket_win_rate": 0.48128727123174997,
    "usable_for_strategy_research": true,
    "reason": "weak_signal"
  },
  {
    "timeframe": "5m",
    "horizon": 6,
    "source_group": "candle_only",
    "feature": "volume_spike_ratio",
    "sample_size": 9972,
    "correlation": -0.005784150944835826,
    "abs_correlation": 0.005784150944835826,
    "quantile_spread": 0.018200193258351517,
    "lowest_bucket_avg_return_pct": -0.002049729796604814,
    "highest_bucket_avg_return_pct": -0.019241735356317242,
    "lowest_bucket_win_rate": 0.5125376128385155,
    "highest_bucket_win_rate": 0.4882205513784461,
    "usable_for_strategy_research": true,
    "reason": "weak_signal"
  },
  {
    "timeframe": "5m",
    "horizon": 1,
    "source_group": "candle_only",
    "feature": "lower_wick_pct",
    "sample_size": 9997,
    "correlation": -0.005702039249802391,
    "abs_correlation": 0.005702039249802391,
    "quantile_spread": 0.006407329529968582,
    "lowest_bucket_avg_return_pct": -0.0011953683717109624,
    "highest_bucket_avg_return_pct": 0.00041687007879299715,
    "lowest_bucket_win_rate": 0.5087543771885943,
    "highest_bucket_win_rate": 0.492,
    "usable_for_strategy_research": true,
    "reason": "weak_signal"
  },
  {
    "timeframe": "5m",
    "horizon": 1,
    "source_group": "candle_only",
    "feature": "volume_spike_ratio",
    "sample_size": 9977,
    "correlation": -0.0050073847669444395,
    "abs_correlation": 0.0050073847669444395,
    "quantile_spread": 0.005233493947682077,
    "lowest_bucket_avg_return_pct": -0.001386419281862114,
    "highest_bucket_avg_return_pct": -0.00016225225012341484,
    "lowest_bucket_win_rate": 0.5007518796992482,
    "highest_bucket_win_rate": 0.503006012024048,
    "usable_for_strategy_research": true,
    "reason": "weak_signal"
  },
  {
    "timeframe": "1m",
    "horizon": 3,
    "source_group": "agg_trade_pressure",
    "feature": "quote_volume_intensity",
    "sample_size": 790,
    "correlation": -0.004964187577688813,
    "abs_correlation": 0.004964187577688813,
    "quantile_spread": 0.0146744388683139,
    "lowest_bucket_avg_return_pct": 0.0006781366842975547,
    "highest_bucket_avg_return_pct": -0.004320865801024701,
    "lowest_bucket_win_rate": 0.46835443037974683,
    "highest_bucket_win_rate": 0.4810126582278481,
    "usable_for_strategy_research": true,
    "reason": "weak_signal"
  },
  {
    "timeframe": "1m",
    "horizon": 3,
    "source_group": "agg_trade_pressure",
    "feature": "avg_trade_quote_size",
    "sample_size": 790,
    "correlation": -0.00494711904902059,
    "abs_correlation": 0.00494711904902059,
    "quantile_spread": 0.014703391464716352,
    "lowest_bucket_avg_return_pct": 0.007715765591805641,
    "highest_bucket_avg_return_pct": -0.006092646088994117,
    "lowest_bucket_win_rate": 0.5126582278481012,
    "highest_bucket_win_rate": 0.4620253164556962,
    "usable_for_strategy_research": true,
    "reason": "weak_signal"
  },
  {
    "timeframe": "5m",
    "horizon": 1,
    "source_group": "candle_only",
    "feature": "body_pct",
    "sample_size": 9997,
    "correlation": 0.004196721489913298,
    "abs_correlation": 0.004196721489913298,
    "quantile_spread": 0.006174592424666343,
    "lowest_bucket_avg_return_pct": 0.0010412165096008556,
    "highest_bucket_avg_return_pct": -0.0009617325393027424,
    "lowest_bucket_win_rate": 0.48774387193596797,
    "highest_bucket_win_rate": 0.4925,
    "usable_for_strategy_research": true,
    "reason": "weak_signal"
  },
  {
    "timeframe": "1m",
    "horizon": 6,
    "source_group": "candle_only",
    "feature": "upper_wick_pct",
    "sample_size": 49994,
    "correlation": 0.002683762929225964,
    "abs_correlation": 0.002683762929225964,
    "quantile_spread": 0.006261353476955375,
    "lowest_bucket_avg_return_pct": 0.0005735497544326355,
    "highest_bucket_avg_return_pct": -0.004546273653229818,
    "lowest_bucket_win_rate": 0.5059011802360472,
    "highest_bucket_win_rate": 0.48064806480648065,
    "usable_for_strategy_research": true,
    "reason": "weak_signal"
  },
  {
    "timeframe": "1m",
    "horizon": 1,
    "source_group": "candle_only",
    "feature": "volume_spike_ratio",
    "sample_size": 49979,
    "correlation": -0.0018226645527874752,
    "abs_correlation": 0.0018226645527874752,
    "quantile_spread": 0.0017052297290384914,
    "lowest_bucket_avg_return_pct": 0.0005172271635208131,
    "highest_bucket_avg_return_pct": -0.0005170145858716501,
    "lowest_bucket_win_rate": 0.4897448724362181,
    "highest_bucket_win_rate": 0.48359343737495,
    "usable_for_strategy_research": true,
    "reason": "weak_signal"
  },
  {
    "timeframe": "1m",
    "horizon": 1,
    "source_group": "candle_only",
    "feature": "upper_wick_pct",
    "sample_size": 49999,
    "correlation": -0.001375288465013959,
    "abs_correlation": 0.001375288465013959,
    "quantile_spread": 0.004123617524966205,
    "lowest_bucket_avg_return_pct": 0.0011844154806486798,
    "highest_bucket_avg_return_pct": -0.001701741996067588,
    "lowest_bucket_win_rate": 0.49104910491049103,
    "highest_bucket_win_rate": 0.4804,
    "usable_for_strategy_research": true,
    "reason": "weak_signal"
  },
  {
    "timeframe": "1m",
    "horizon": 1,
    "source_group": "agg_trade_pressure",
    "feature": "avg_trade_quote_size",
    "sample_size": 790,
    "correlation": -0.0010943985178073117,
    "abs_correlation": 0.0010943985178073117,
    "quantile_spread": 0.004989906613969103,
    "lowest_bucket_avg_return_pct": 0.0025821703175261195,
    "highest_bucket_avg_return_pct": -0.0018596546048383201,
    "lowest_bucket_win_rate": 0.5632911392405063,
    "highest_bucket_win_rate": 0.46835443037974683,
    "usable_for_strategy_research": true,
    "reason": "weak_signal"
  },
  {
    "timeframe": "15m",
    "horizon": 3,
    "source_group": "live_order_book",
    "feature": "spread_pct",
    "sample_size": 17,
    "correlation": -0.38880101850170445,
    "abs_correlation": 0.38880101850170445,
    "quantile_spread": 0.8116968220226275,
    "lowest_bucket_avg_return_pct": 0.6710598177404639,
    "highest_bucket_avg_return_pct": 0.14212029706090767,
    "lowest_bucket_win_rate": 0.6666666666666666,
    "highest_bucket_win_rate": 0.5,
    "usable_for_strategy_research": false,
    "reason": "not_enough_samples"
  },
  {
    "timeframe": "15m",
    "horizon": 6,
    "source_group": "agg_trade_pressure",
    "feature": "trade_count_intensity",
    "sample_size": 52,
    "correlation": -0.3881300385636933,
    "abs_correlation": 0.3881300385636933,
    "quantile_spread": 0.2693697979002946,
    "lowest_bucket_avg_return_pct": 0.09542659412036425,
    "highest_bucket_avg_return_pct": -0.12194585251622109,
    "lowest_bucket_win_rate": 0.8,
    "highest_bucket_win_rate": 0.18181818181818182,
    "usable_for_strategy_research": false,
    "reason": "not_enough_samples"
  },
  {
    "timeframe": "15m",
    "horizon": 3,
    "source_group": "agg_trade_pressure",
    "feature": "trade_count_intensity",
    "sample_size": 52,
    "correlation": -0.3875529171186761,
    "abs_correlation": 0.3875529171186761,
    "quantile_spread": 0.22506290917117028,
    "lowest_bucket_avg_return_pct": 0.048002662077986744,
    "highest_bucket_avg_return_pct": -0.08864962706963969,
    "lowest_bucket_win_rate": 0.9,
    "highest_bucket_win_rate": 0.18181818181818182,
    "usable_for_strategy_research": false,
    "reason": "not_enough_samples"
  },
  {
    "timeframe": "15m",
    "horizon": 6,
    "source_group": "live_order_book",
    "feature": "spread_pct",
    "sample_size": 17,
    "correlation": -0.3751110853491355,
    "abs_correlation": 0.3751110853491355,
    "quantile_spread": 1.3554670504268427,
    "lowest_bucket_avg_return_pct": 0.5548088876649098,
    "highest_bucket_avg_return_pct": 0.3740636577838089,
    "lowest_bucket_win_rate": 1.0,
    "highest_bucket_win_rate": 0.75,
    "usable_for_strategy_research": false,
    "reason": "not_enough_samples"
  },
  {
    "timeframe": "5m",
    "horizon": 3,
    "source_group": "live_order_book",
    "feature": "imbalance_top_20",
    "sample_size": 46,
    "correlation": 0.34038152649191744,
    "abs_correlation": 0.34038152649191744,
    "quantile_spread": 0.6275733843563758,
    "lowest_bucket_avg_return_pct": -0.03075742603274139,
    "highest_bucket_avg_return_pct": 0.4136410577094972,
    "lowest_bucket_win_rate": 0.4444444444444444,
    "highest_bucket_win_rate": 0.6,
    "usable_for_strategy_research": false,
    "reason": "not_enough_samples"
  },
  {
    "timeframe": "15m",
    "horizon": 1,
    "source_group": "live_order_book",
    "feature": "spread_pct",
    "sample_size": 17,
    "correlation": -0.3315966073426554,
    "abs_correlation": 0.3315966073426554,
    "quantile_spread": 0.4531011092976771,
    "lowest_bucket_avg_return_pct": -0.08165246826536096,
    "highest_bucket_avg_return_pct": -0.07424474997714678,
    "lowest_bucket_win_rate": 0.3333333333333333,
    "highest_bucket_win_rate": 0.5,
    "usable_for_strategy_research": false,
    "reason": "not_enough_samples"
  },
  {
    "timeframe": "15m",
    "horizon": 3,
    "source_group": "agg_trade_pressure",
    "feature": "taker_buy_base_ratio_trades",
    "sample_size": 52,
    "correlation": -0.2960743012866577,
    "abs_correlation": 0.2960743012866577,
    "quantile_spread": 0.16077382601405588,
    "lowest_bucket_avg_return_pct": 0.04577005299178498,
    "highest_bucket_avg_return_pct": -0.11500377302227091,
    "lowest_bucket_win_rate": 0.7,
    "highest_bucket_win_rate": 0.2727272727272727,
    "usable_for_strategy_research": false,
    "reason": "not_enough_samples"
  },
  {
    "timeframe": "15m",
    "horizon": 3,
    "source_group": "agg_trade_pressure",
    "feature": "taker_buy_quote_ratio_trades",
    "sample_size": 52,
    "correlation": -0.2960607973192747,
    "abs_correlation": 0.2960607973192747,
    "quantile_spread": 0.16077382601405588,
    "lowest_bucket_avg_return_pct": 0.04577005299178498,
    "highest_bucket_avg_return_pct": -0.11500377302227091,
    "lowest_bucket_win_rate": 0.7,
    "highest_bucket_win_rate": 0.2727272727272727,
    "usable_for_strategy_research": false,
    "reason": "not_enough_samples"
  },
  {
    "timeframe": "5m",
    "horizon": 3,
    "source_group": "live_order_book",
    "feature": "order_book_imbalance",
    "sample_size": 46,
    "correlation": 0.2793753339039131,
    "abs_correlation": 0.2793753339039131,
    "quantile_spread": 0.3603297169315346,
    "lowest_bucket_avg_return_pct": 0.026812225756639038,
    "highest_bucket_avg_return_pct": 0.3279087630819524,
    "lowest_bucket_win_rate": 0.4444444444444444,
    "highest_bucket_win_rate": 0.7,
    "usable_for_strategy_research": false,
    "reason": "not_enough_samples"
  },
  {
    "timeframe": "5m",
    "horizon": 3,
    "source_group": "live_order_book",
    "feature": "imbalance_top_10",
    "sample_size": 46,
    "correlation": 0.2793753339039131,
    "abs_correlation": 0.2793753339039131,
    "quantile_spread": 0.3603297169315346,
    "lowest_bucket_avg_return_pct": 0.026812225756639038,
    "highest_bucket_avg_return_pct": 0.3279087630819524,
    "lowest_bucket_win_rate": 0.4444444444444444,
    "highest_bucket_win_rate": 0.7,
    "usable_for_strategy_research": false,
    "reason": "not_enough_samples"
  },
  {
    "timeframe": "15m",
    "horizon": 6,
    "source_group": "agg_trade_pressure",
    "feature": "taker_buy_trade_ratio",
    "sample_size": 52,
    "correlation": 0.2707132604439036,
    "abs_correlation": 0.2707132604439036,
    "quantile_spread": 0.266459452188582,
    "lowest_bucket_avg_return_pct": -0.06606901481057335,
    "highest_bucket_avg_return_pct": 0.07942476458006692,
    "lowest_bucket_win_rate": 0.3,
    "highest_bucket_win_rate": 0.6363636363636364,
    "usable_for_strategy_research": false,
    "reason": "not_enough_samples"
  },
  {
    "timeframe": "5m",
    "horizon": 3,
    "source_group": "live_order_book",
    "feature": "imbalance_top_5",
    "sample_size": 46,
    "correlation": 0.2634678720404744,
    "abs_correlation": 0.2634678720404744,
    "quantile_spread": 0.3241960635876176,
    "lowest_bucket_avg_return_pct": 0.033187005183594534,
    "highest_bucket_avg_return_pct": 0.3279087630819524,
    "lowest_bucket_win_rate": 0.4444444444444444,
    "highest_bucket_win_rate": 0.7,
    "usable_for_strategy_research": false,
    "reason": "not_enough_samples"
  },
  {
    "timeframe": "5m",
    "horizon": 6,
    "source_group": "live_order_book",
    "feature": "imbalance_top_20",
    "sample_size": 46,
    "correlation": 0.253180909280685,
    "abs_correlation": 0.253180909280685,
    "quantile_spread": 0.4916141430788582,
    "lowest_bucket_avg_return_pct": -0.046138575672320076,
    "highest_bucket_avg_return_pct": 0.44547556740653815,
    "lowest_bucket_win_rate": 0.4444444444444444,
    "highest_bucket_win_rate": 0.6,
    "usable_for_strategy_research": false,
    "reason": "not_enough_samples"
  },
  {
    "timeframe": "15m",
    "horizon": 3,
    "source_group": "agg_trade_pressure",
    "feature": "taker_net_quote_volume",
    "sample_size": 52,
    "correlation": -0.24264951409277444,
    "abs_correlation": 0.24264951409277444,
    "quantile_spread": 0.1723328398329053,
    "lowest_bucket_avg_return_pct": 0.061492691791878086,
    "highest_bucket_avg_return_pct": -0.11084014804102721,
    "lowest_bucket_win_rate": 0.7,
    "highest_bucket_win_rate": 0.2727272727272727,
    "usable_for_strategy_research": false,
    "reason": "not_enough_samples"
  },
  {
    "timeframe": "15m",
    "horizon": 3,
    "source_group": "agg_trade_pressure",
    "feature": "taker_net_base_volume",
    "sample_size": 52,
    "correlation": -0.2426409403733507,
    "abs_correlation": 0.2426409403733507,
    "quantile_spread": 0.1723328398329053,
    "lowest_bucket_avg_return_pct": 0.061492691791878086,
    "highest_bucket_avg_return_pct": -0.11084014804102721,
    "lowest_bucket_win_rate": 0.7,
    "highest_bucket_win_rate": 0.2727272727272727,
    "usable_for_strategy_research": false,
    "reason": "not_enough_samples"
  },
  {
    "timeframe": "15m",
    "horizon": 3,
    "source_group": "agg_trade_pressure",
    "feature": "quote_volume_intensity",
    "sample_size": 52,
    "correlation": -0.24091676240201212,
    "abs_correlation": 0.24091676240201212,
    "quantile_spread": 0.15504528032377762,
    "lowest_bucket_avg_return_pct": 0.047695711797344956,
    "highest_bucket_avg_return_pct": -0.10734956852643265,
    "lowest_bucket_win_rate": 0.7,
    "highest_bucket_win_rate": 0.18181818181818182,
    "usable_for_strategy_research": false,
    "reason": "not_enough_samples"
  },
  {
    "timeframe": "5m",
    "horizon": 1,
    "source_group": "live_order_book",
    "feature": "imbalance_top_20",
    "sample_size": 46,
    "correlation": 0.2369550222818093,
    "abs_correlation": 0.2369550222818093,
    "quantile_spread": 0.22146104540518685,
    "lowest_bucket_avg_return_pct": -0.1105224356596788,
    "highest_bucket_avg_return_pct": 0.11093860974550804,
    "lowest_bucket_win_rate": 0.3333333333333333,
    "highest_bucket_win_rate": 0.6,
    "usable_for_strategy_research": false,
    "reason": "not_enough_samples"
  },
  {
    "timeframe": "15m",
    "horizon": 6,
    "source_group": "live_order_book",
    "feature": "imbalance_top_20",
    "sample_size": 17,
    "correlation": 0.23209849008443525,
    "abs_correlation": 0.23209849008443525,
    "quantile_spread": 1.118915009437727,
    "lowest_bucket_avg_return_pct": 0.22624886767247485,
    "highest_bucket_avg_return_pct": 0.6027777382904588,
    "lowest_bucket_win_rate": 0.6666666666666666,
    "highest_bucket_win_rate": 0.75,
    "usable_for_strategy_research": false,
    "reason": "not_enough_samples"
  },
  {
    "timeframe": "5m",
    "horizon": 6,
    "source_group": "live_order_book",
    "feature": "spread_pct",
    "sample_size": 46,
    "correlation": -0.21945126994109196,
    "abs_correlation": 0.21945126994109196,
    "quantile_spread": 0.7192199241244834,
    "lowest_bucket_avg_return_pct": -0.14186173067136457,
    "highest_bucket_avg_return_pct": 0.10294784725073156,
    "lowest_bucket_win_rate": 0.2222222222222222,
    "highest_bucket_win_rate": 0.7,
    "usable_for_strategy_research": false,
    "reason": "not_enough_samples"
  },
  {
    "timeframe": "15m",
    "horizon": 6,
    "source_group": "live_order_book",
    "feature": "order_book_imbalance",
    "sample_size": 17,
    "correlation": 0.21598637560791048,
    "abs_correlation": 0.21598637560791048,
    "quantile_spread": 0.6629925604650682,
    "lowest_bucket_avg_return_pct": 0.22624886767247485,
    "highest_bucket_avg_return_pct": 0.5607195710854106,
    "lowest_bucket_win_rate": 0.6666666666666666,
    "highest_bucket_win_rate": 0.75,
    "usable_for_strategy_research": false,
    "reason": "not_enough_samples"
  },
  {
    "timeframe": "15m",
    "horizon": 6,
    "source_group": "live_order_book",
    "feature": "imbalance_top_10",
    "sample_size": 17,
    "correlation": 0.21598637560791048,
    "abs_correlation": 0.21598637560791048,
    "quantile_spread": 0.6629925604650682,
    "lowest_bucket_avg_return_pct": 0.22624886767247485,
    "highest_bucket_avg_return_pct": 0.5607195710854106,
    "lowest_bucket_win_rate": 0.6666666666666666,
    "highest_bucket_win_rate": 0.75,
    "usable_for_strategy_research": false,
    "reason": "not_enough_samples"
  },
  {
    "timeframe": "15m",
    "horizon": 1,
    "source_group": "agg_trade_pressure",
    "feature": "avg_trade_quote_size",
    "sample_size": 52,
    "correlation": 0.21472712297103907,
    "abs_correlation": 0.21472712297103907,
    "quantile_spread": 0.07740317170957406,
    "lowest_bucket_avg_return_pct": -0.044182251187512886,
    "highest_bucket_avg_return_pct": 0.015542158785392167,
    "lowest_bucket_win_rate": 0.4,
    "highest_bucket_win_rate": 0.5454545454545454,
    "usable_for_strategy_research": false,
    "reason": "not_enough_samples"
  },
  {
    "timeframe": "5m",
    "horizon": 1,
    "source_group": "live_order_book",
    "feature": "order_book_imbalance",
    "sample_size": 46,
    "correlation": 0.21176978071032124,
    "abs_correlation": 0.21176978071032124,
    "quantile_spread": 0.20593883552205167,
    "lowest_bucket_avg_return_pct": -0.025590984080642795,
    "highest_bucket_avg_return_pct": 0.1481694529970902,
    "lowest_bucket_win_rate": 0.3333333333333333,
    "highest_bucket_win_rate": 0.7,
    "usable_for_strategy_research": false,
    "reason": "not_enough_samples"
  },
  {
    "timeframe": "5m",
    "horizon": 1,
    "source_group": "live_order_book",
    "feature": "imbalance_top_10",
    "sample_size": 46,
    "correlation": 0.21176978071032124,
    "abs_correlation": 0.21176978071032124,
    "quantile_spread": 0.20593883552205167,
    "lowest_bucket_avg_return_pct": -0.025590984080642795,
    "highest_bucket_avg_return_pct": 0.1481694529970902,
    "lowest_bucket_win_rate": 0.3333333333333333,
    "highest_bucket_win_rate": 0.7,
    "usable_for_strategy_research": false,
    "reason": "not_enough_samples"
  },
  {
    "timeframe": "5m",
    "horizon": 1,
    "source_group": "live_order_book",
    "feature": "imbalance_top_5",
    "sample_size": 46,
    "correlation": 0.20870949820253815,
    "abs_correlation": 0.20870949820253815,
    "quantile_spread": 0.1978872470599211,
    "lowest_bucket_avg_return_pct": -0.0032473289822530383,
    "highest_bucket_avg_return_pct": 0.1481694529970902,
    "lowest_bucket_win_rate": 0.4444444444444444,
    "highest_bucket_win_rate": 0.7,
    "usable_for_strategy_research": false,
    "reason": "not_enough_samples"
  },
  {
    "timeframe": "15m",
    "horizon": 6,
    "source_group": "live_order_book",
    "feature": "imbalance_top_5",
    "sample_size": 17,
    "correlation": 0.2080094025322227,
    "abs_correlation": 0.2080094025322227,
    "quantile_spread": 0.6629925604650682,
    "lowest_bucket_avg_return_pct": 0.22624886767247485,
    "highest_bucket_avg_return_pct": 0.5607195710854106,
    "lowest_bucket_win_rate": 0.6666666666666666,
    "highest_bucket_win_rate": 0.75,
    "usable_for_strategy_research": false,
    "reason": "not_enough_samples"
  },
  {
    "timeframe": "15m",
    "horizon": 1,
    "source_group": "agg_trade_pressure",
    "feature": "taker_buy_base_ratio_trades",
    "sample_size": 52,
    "correlation": -0.18832780724767798,
    "abs_correlation": 0.18832780724767798,
    "quantile_spread": 0.11111906297531964,
    "lowest_bucket_avg_return_pct": 0.014767791065299402,
    "highest_bucket_avg_return_pct": -0.061323844850577756,
    "lowest_bucket_win_rate": 0.6,
    "highest_bucket_win_rate": 0.18181818181818182,
    "usable_for_strategy_research": false,
    "reason": "not_enough_samples"
  },
  {
    "timeframe": "15m",
    "horizon": 1,
    "source_group": "agg_trade_pressure",
    "feature": "taker_buy_quote_ratio_trades",
    "sample_size": 52,
    "correlation": -0.18830137071988365,
    "abs_correlation": 0.18830137071988365,
    "quantile_spread": 0.11111906297531964,
    "lowest_bucket_avg_return_pct": 0.014767791065299402,
    "highest_bucket_avg_return_pct": -0.061323844850577756,
    "lowest_bucket_win_rate": 0.6,
    "highest_bucket_win_rate": 0.18181818181818182,
    "usable_for_strategy_research": false,
    "reason": "not_enough_samples"
  },
  {
    "timeframe": "15m",
    "horizon": 1,
    "source_group": "agg_trade_pressure",
    "feature": "quote_volume_intensity",
    "sample_size": 52,
    "correlation": 0.1830700378547317,
    "abs_correlation": 0.1830700378547317,
    "quantile_spread": 0.07397906275524266,
    "lowest_bucket_avg_return_pct": -0.007143182632181061,
    "highest_bucket_avg_return_pct": 0.01127055807145869,
    "lowest_bucket_win_rate": 0.4,
    "highest_bucket_win_rate": 0.45454545454545453,
    "usable_for_strategy_research": false,
    "reason": "not_enough_samples"
  },
  {
    "timeframe": "15m",
    "horizon": 6,
    "source_group": "agg_trade_pressure",
    "feature": "avg_trade_quote_size",
    "sample_size": 52,
    "correlation": 0.1711930195768751,
    "abs_correlation": 0.1711930195768751,
    "quantile_spread": 0.08550479231926217,
    "lowest_bucket_avg_return_pct": -0.09273027261528277,
    "highest_bucket_avg_return_pct": -0.01193652580643419,
    "lowest_bucket_win_rate": 0.3,
    "highest_bucket_win_rate": 0.45454545454545453,
    "usable_for_strategy_research": false,
    "reason": "not_enough_samples"
  },
  {
    "timeframe": "5m",
    "horizon": 6,
    "source_group": "live_order_book",
    "feature": "order_book_imbalance",
    "sample_size": 46,
    "correlation": 0.1698561484160138,
    "abs_correlation": 0.1698561484160138,
    "quantile_spread": 0.3197200490868577,
    "lowest_bucket_avg_return_pct": 0.09707738606665577,
    "highest_bucket_avg_return_pct": 0.37323467385817505,
    "lowest_bucket_win_rate": 0.4444444444444444,
    "highest_bucket_win_rate": 0.7,
    "usable_for_strategy_research": false,
    "reason": "not_enough_samples"
  },
  {
    "timeframe": "5m",
    "horizon": 6,
    "source_group": "live_order_book",
    "feature": "imbalance_top_10",
    "sample_size": 46,
    "correlation": 0.1698561484160138,
    "abs_correlation": 0.1698561484160138,
    "quantile_spread": 0.3197200490868577,
    "lowest_bucket_avg_return_pct": 0.09707738606665577,
    "highest_bucket_avg_return_pct": 0.37323467385817505,
    "lowest_bucket_win_rate": 0.4444444444444444,
    "highest_bucket_win_rate": 0.7,
    "usable_for_strategy_research": false,
    "reason": "not_enough_samples"
  },
  {
    "timeframe": "5m",
    "horizon": 3,
    "source_group": "live_order_book",
    "feature": "spread_pct",
    "sample_size": 46,
    "correlation": -0.1656712886060634,
    "abs_correlation": 0.1656712886060634,
    "quantile_spread": 0.4580282444107891,
    "lowest_bucket_avg_return_pct": -0.025794342672229825,
    "highest_bucket_avg_return_pct": 0.013284797363119018,
    "lowest_bucket_win_rate": 0.3333333333333333,
    "highest_bucket_win_rate": 0.7,
    "usable_for_strategy_research": false,
    "reason": "not_enough_samples"
  },
  {
    "timeframe": "15m",
    "horizon": 6,
    "source_group": "agg_trade_pressure",
    "feature": "taker_buy_base_ratio_trades",
    "sample_size": 52,
    "correlation": -0.14126807811051162,
    "abs_correlation": 0.14126807811051162,
    "quantile_spread": 0.12459395828823543,
    "lowest_bucket_avg_return_pct": 0.022307690666362373,
    "highest_bucket_avg_return_pct": -0.06331367735903126,
    "lowest_bucket_win_rate": 0.6,
    "highest_bucket_win_rate": 0.36363636363636365,
    "usable_for_strategy_research": false,
    "reason": "not_enough_samples"
  },
  {
    "timeframe": "15m",
    "horizon": 6,
    "source_group": "agg_trade_pressure",
    "feature": "taker_buy_quote_ratio_trades",
    "sample_size": 52,
    "correlation": -0.14125930764765923,
    "abs_correlation": 0.14125930764765923,
    "quantile_spread": 0.12459395828823543,
    "lowest_bucket_avg_return_pct": 0.022307690666362373,
    "highest_bucket_avg_return_pct": -0.06331367735903126,
    "lowest_bucket_win_rate": 0.6,
    "highest_bucket_win_rate": 0.36363636363636365,
    "usable_for_strategy_research": false,
    "reason": "not_enough_samples"
  },
  {
    "timeframe": "5m",
    "horizon": 6,
    "source_group": "live_order_book",
    "feature": "imbalance_top_5",
    "sample_size": 46,
    "correlation": 0.13899014132182202,
    "abs_correlation": 0.13899014132182202,
    "quantile_spread": 0.350199770454848,
    "lowest_bucket_avg_return_pct": 0.11373938360718504,
    "highest_bucket_avg_return_pct": 0.37323467385817505,
    "lowest_bucket_win_rate": 0.4444444444444444,
    "highest_bucket_win_rate": 0.7,
    "usable_for_strategy_research": false,
    "reason": "not_enough_samples"
  },
  {
    "timeframe": "15m",
    "horizon": 3,
    "source_group": "live_order_book",
    "feature": "imbalance_top_5",
    "sample_size": 17,
    "correlation": -0.11790420462777504,
    "abs_correlation": 0.11790420462777504,
    "quantile_spread": 1.017900549120181,
    "lowest_bucket_avg_return_pct": 0.32927311835078693,
    "highest_bucket_avg_return_pct": 0.13428916597138146,
    "lowest_bucket_win_rate": 0.6666666666666666,
    "highest_bucket_win_rate": 0.75,
    "usable_for_strategy_research": false,
    "reason": "not_enough_samples"
  },
  {
    "timeframe": "15m",
    "horizon": 1,
    "source_group": "agg_trade_pressure",
    "feature": "taker_net_base_volume",
    "sample_size": 52,
    "correlation": -0.10947959197429029,
    "abs_correlation": 0.10947959197429029,
    "quantile_spread": 0.12305888569162583,
    "lowest_bucket_avg_return_pct": 0.059937627302976235,
    "highest_bucket_avg_return_pct": -0.01688554018106071,
    "lowest_bucket_win_rate": 0.8,
    "highest_bucket_win_rate": 0.36363636363636365,
    "usable_for_strategy_research": false,
    "reason": "not_enough_samples"
  },
  {
    "timeframe": "15m",
    "horizon": 1,
    "source_group": "agg_trade_pressure",
    "feature": "taker_net_quote_volume",
    "sample_size": 52,
    "correlation": -0.10928321855692866,
    "abs_correlation": 0.10928321855692866,
    "quantile_spread": 0.12305888569162583,
    "lowest_bucket_avg_return_pct": 0.059937627302976235,
    "highest_bucket_avg_return_pct": -0.01688554018106071,
    "lowest_bucket_win_rate": 0.8,
    "highest_bucket_win_rate": 0.36363636363636365,
    "usable_for_strategy_research": false,
    "reason": "not_enough_samples"
  },
  {
    "timeframe": "15m",
    "horizon": 1,
    "source_group": "agg_trade_pressure",
    "feature": "taker_buy_trade_ratio",
    "sample_size": 52,
    "correlation": -0.10769656441149889,
    "abs_correlation": 0.10769656441149889,
    "quantile_spread": 0.06990756595725324,
    "lowest_bucket_avg_return_pct": 0.02434746268845005,
    "highest_bucket_avg_return_pct": 0.0012448097776496232,
    "lowest_bucket_win_rate": 0.5,
    "highest_bucket_win_rate": 0.5454545454545454,
    "usable_for_strategy_research": false,
    "reason": "not_enough_samples"
  },
  {
    "timeframe": "15m",
    "horizon": 3,
    "source_group": "agg_trade_pressure",
    "feature": "taker_buy_trade_ratio",
    "sample_size": 52,
    "correlation": 0.10491080524587103,
    "abs_correlation": 0.10491080524587103,
    "quantile_spread": 0.12125608454551622,
    "lowest_bucket_avg_return_pct": 0.002606514884262011,
    "highest_bucket_avg_return_pct": 0.018200147714820588,
    "lowest_bucket_win_rate": 0.6,
    "highest_bucket_win_rate": 0.7272727272727273,
    "usable_for_strategy_research": false,
    "reason": "not_enough_samples"
  },
  {
    "timeframe": "15m",
    "horizon": 3,
    "source_group": "live_order_book",
    "feature": "order_book_imbalance",
    "sample_size": 17,
    "correlation": -0.0916383293096445,
    "abs_correlation": 0.0916383293096445,
    "quantile_spread": 1.017900549120181,
    "lowest_bucket_avg_return_pct": 0.32927311835078693,
    "highest_bucket_avg_return_pct": 0.13428916597138146,
    "lowest_bucket_win_rate": 0.6666666666666666,
    "highest_bucket_win_rate": 0.75,
    "usable_for_strategy_research": false,
    "reason": "not_enough_samples"
  },
  {
    "timeframe": "15m",
    "horizon": 3,
    "source_group": "live_order_book",
    "feature": "imbalance_top_10",
    "sample_size": 17,
    "correlation": -0.0916383293096445,
    "abs_correlation": 0.0916383293096445,
    "quantile_spread": 1.017900549120181,
    "lowest_bucket_avg_return_pct": 0.32927311835078693,
    "highest_bucket_avg_return_pct": 0.13428916597138146,
    "lowest_bucket_win_rate": 0.6666666666666666,
    "highest_bucket_win_rate": 0.75,
    "usable_for_strategy_research": false,
    "reason": "not_enough_samples"
  },
  {
    "timeframe": "15m",
    "horizon": 1,
    "source_group": "live_order_book",
    "feature": "imbalance_top_20",
    "sample_size": 17,
    "correlation": 0.08843425346905262,
    "abs_correlation": 0.08843425346905262,
    "quantile_spread": 0.6563253234558057,
    "lowest_bucket_avg_return_pct": 0.060175077624589596,
    "highest_bucket_avg_return_pct": 0.27267706431419725,
    "lowest_bucket_win_rate": 0.6666666666666666,
    "highest_bucket_win_rate": 1.0,
    "usable_for_strategy_research": false,
    "reason": "not_enough_samples"
  },
  {
    "timeframe": "15m",
    "horizon": 6,
    "source_group": "agg_trade_pressure",
    "feature": "taker_net_quote_volume",
    "sample_size": 52,
    "correlation": -0.07749095864594485,
    "abs_correlation": 0.07749095864594485,
    "quantile_spread": 0.27345812957356663,
    "lowest_bucket_avg_return_pct": 0.07080786556055271,
    "highest_bucket_avg_return_pct": -0.09736616654324276,
    "lowest_bucket_win_rate": 0.6,
    "highest_bucket_win_rate": 0.36363636363636365,
    "usable_for_strategy_research": false,
    "reason": "not_enough_samples"
  },
  {
    "timeframe": "15m",
    "horizon": 6,
    "source_group": "agg_trade_pressure",
    "feature": "taker_net_base_volume",
    "sample_size": 52,
    "correlation": -0.07729223087691604,
    "abs_correlation": 0.07729223087691604,
    "quantile_spread": 0.27345812957356663,
    "lowest_bucket_avg_return_pct": 0.07080786556055271,
    "highest_bucket_avg_return_pct": -0.09736616654324276,
    "lowest_bucket_win_rate": 0.6,
    "highest_bucket_win_rate": 0.36363636363636365,
    "usable_for_strategy_research": false,
    "reason": "not_enough_samples"
  },
  {
    "timeframe": "15m",
    "horizon": 6,
    "source_group": "agg_trade_pressure",
    "feature": "quote_volume_intensity",
    "sample_size": 52,
    "correlation": -0.07233397120990624,
    "abs_correlation": 0.07233397120990624,
    "quantile_spread": 0.1253219402343248,
    "lowest_bucket_avg_return_pct": 0.03509671224470086,
    "highest_bucket_avg_return_pct": -0.08438413991146884,
    "lowest_bucket_win_rate": 0.7,
    "highest_bucket_win_rate": 0.2727272727272727,
    "usable_for_strategy_research": false,
    "reason": "not_enough_samples"
  },
  {
    "timeframe": "15m",
    "horizon": 1,
    "source_group": "agg_trade_pressure",
    "feature": "trade_count_intensity",
    "sample_size": 52,
    "correlation": 0.034712563391662815,
    "abs_correlation": 0.034712563391662815,
    "quantile_spread": 0.08600257909405866,
    "lowest_bucket_avg_return_pct": 0.01147029252018902,
    "highest_bucket_avg_return_pct": -0.009253658547692313,
    "lowest_bucket_win_rate": 0.6,
    "highest_bucket_win_rate": 0.36363636363636365,
    "usable_for_strategy_research": false,
    "reason": "not_enough_samples"
  },
  {
    "timeframe": "15m",
    "horizon": 3,
    "source_group": "agg_trade_pressure",
    "feature": "avg_trade_quote_size",
    "sample_size": 52,
    "correlation": -0.03396909631544899,
    "abs_correlation": 0.03396909631544899,
    "quantile_spread": 0.06917154670830883,
    "lowest_bucket_avg_return_pct": -0.017962748017062262,
    "highest_bucket_avg_return_pct": -0.06574281491756197,
    "lowest_bucket_win_rate": 0.4,
    "highest_bucket_win_rate": 0.36363636363636365,
    "usable_for_strategy_research": false,
    "reason": "not_enough_samples"
  },
  {
    "timeframe": "15m",
    "horizon": 1,
    "source_group": "live_order_book",
    "feature": "order_book_imbalance",
    "sample_size": 17,
    "correlation": 0.021186558264840144,
    "abs_correlation": 0.021186558264840144,
    "quantile_spread": 0.5582095755631247,
    "lowest_bucket_avg_return_pct": 0.060175077624589596,
    "highest_bucket_avg_return_pct": 0.21309148690033977,
    "lowest_bucket_win_rate": 0.6666666666666666,
    "highest_bucket_win_rate": 0.75,
    "usable_for_strategy_research": false,
    "reason": "not_enough_samples"
  },
  {
    "timeframe": "15m",
    "horizon": 1,
    "source_group": "live_order_book",
    "feature": "imbalance_top_10",
    "sample_size": 17,
    "correlation": 0.021186558264840144,
    "abs_correlation": 0.021186558264840144,
    "quantile_spread": 0.5582095755631247,
    "lowest_bucket_avg_return_pct": 0.060175077624589596,
    "highest_bucket_avg_return_pct": 0.21309148690033977,
    "lowest_bucket_win_rate": 0.6666666666666666,
    "highest_bucket_win_rate": 0.75,
    "usable_for_strategy_research": false,
    "reason": "not_enough_samples"
  },
  {
    "timeframe": "5m",
    "horizon": 1,
    "source_group": "live_order_book",
    "feature": "spread_pct",
    "sample_size": 46,
    "correlation": 0.02060049480092785,
    "abs_correlation": 0.02060049480092785,
    "quantile_spread": 0.10168670819332465,
    "lowest_bucket_avg_return_pct": 0.04024611532524461,
    "highest_bucket_avg_return_pct": 0.04364017658419429,
    "lowest_bucket_win_rate": 0.4444444444444444,
    "highest_bucket_win_rate": 0.7,
    "usable_for_strategy_research": false,
    "reason": "not_enough_samples"
  },
  {
    "timeframe": "15m",
    "horizon": 3,
    "source_group": "live_order_book",
    "feature": "imbalance_top_20",
    "sample_size": 17,
    "correlation": -0.011008070708886162,
    "abs_correlation": 0.011008070708886162,
    "quantile_spread": 0.8078943631422781,
    "lowest_bucket_avg_return_pct": 0.32927311835078693,
    "highest_bucket_avg_return_pct": 0.4388103917266976,
    "lowest_bucket_win_rate": 0.6666666666666666,
    "highest_bucket_win_rate": 1.0,
    "usable_for_strategy_research": false,
    "reason": "not_enough_samples"
  },
  {
    "timeframe": "15m",
    "horizon": 1,
    "source_group": "live_order_book",
    "feature": "imbalance_top_5",
    "sample_size": 17,
    "correlation": 0.0019192222312421016,
    "abs_correlation": 0.0019192222312421016,
    "quantile_spread": 0.5582095755631247,
    "lowest_bucket_avg_return_pct": 0.060175077624589596,
    "highest_bucket_avg_return_pct": 0.21309148690033977,
    "lowest_bucket_win_rate": 0.6666666666666666,
    "highest_bucket_win_rate": 0.75,
    "usable_for_strategy_research": false,
    "reason": "not_enough_samples"
  }
]